[{"appid": 2683170, "name": "SpaceFront", "last_modified": 1705125386, "price_change_number": 0}, {"appid": 2683180, "name": "Ball of Poo", "last_modified": 1702061969, "price_change_number": 22766324}, {"appid": 2683200, "name": "The Paupers", "last_modified": 1704535835, "price_change_number": 22766324}, {"appid": 2683210, "name": "Watermelon Challenge", "last_modified": 1700503242, "price_change_number": 22766324}, {"appid": 2683250, "name": "Falnarion Tactics III", "last_modified": 1703535770, "price_change_number": 22766324}, {"appid": 2683300, "name": "\u517d\u98df\u6b32:\u94fe\u63a5 Animal appetite\uff1alink", "last_modified": 1701355596, "price_change_number": 21343762}, {"appid": 2683320, "name": "Project Aphotic", "last_modified": 1709275576, "price_change_number": 0}, {"appid": 2683330, "name": "Paradise Inc", "last_modified": 1703560331, "price_change_number": 22766324}, {"appid": 2683350, "name": "GO SOME BALLS", "last_modified": 1705231516, "price_change_number": 0}, {"appid": 2683360, "name": "Error_Boy.exe", "last_modified": 1710001470, "price_change_number": 0}, {"appid": 2683370, "name": "TeleCollision", "last_modified": 1710466769, "price_change_number": 0}, {"appid": 2683490, "name": "Glimpse", "last_modified": 1704548994, "price_change_number": 22766324}, {"appid": 2683510, "name": "\u6253\u5b57\u6218\u6597", "last_modified": 1701085669, "price_change_number": 22766324}, {"appid": 2683520, "name": "Bat Blast!", "last_modified": 1701013901, "price_change_number": 0}, {"appid": 2683550, "name": "\u4f60\u5f88\u806a\u660e\u5417\uff1f", "last_modified": 1709818859, "price_change_number": 0}, {"appid": 2683560, "name": "Alian", "last_modified": 1709593502, "price_change_number": 22630132}, {"appid": 2683570, "name": "Push The Cat with WASD", "last_modified": 1710239281, "price_change_number": 0}, {"appid": 2683580, "name": "The DarkCity", "last_modified": 1700862837, "price_change_number": 0}, {"appid": 2683590, "name": "LYMBUS", "last_modified": 1709394748, "price_change_number": 0}, {"appid": 2683610, "name": "Pizza Delivery [zebaxx]", "last_modified": 1700928185, "price_change_number": 22766324}, {"appid": 2683620, "name": "Circle of Swords", "last_modified": 1700177229, "price_change_number": 0}, {"appid": 2683640, "name": "Sword n' Dragons", "last_modified": 1710318293, "price_change_number": 0}, {"appid": 2683680, "name": "Witch Academy Another Battle", "last_modified": 1701333095, "price_change_number": 22766324}, {"appid": 2683700, "name": "Hieroglyph Quest: The Amarna Enigma", "last_modified": 1700680727, "price_change_number": 0}, {"appid": 2683710, "name": "Cerebral Clash", "last_modified": 1709810632, "price_change_number": 22767894}, {"appid": 2683740, "name": "THE SIREEN", "last_modified": 1710511343, "price_change_number": 0}, {"appid": 2683760, "name": "Blouncy", "last_modified": 1703186210, "price_change_number": 22736671}, {"appid": 2683800, "name": "Hentai Milena", "last_modified": 1700904589, "price_change_number": 22766324}, {"appid": 2683810, "name": "Danny's Descent", "last_modified": 1699573148, "price_change_number": 22736671}, {"appid": 2683960, "name": "Weapon Shop Decillionaire", "last_modified": 1701215935, "price_change_number": 22411605}, {"appid": 2683970, "name": "Ground Parkour : First Mission", "last_modified": 1700761516, "price_change_number": 21786011}, {"appid": 2684010, "name": "Super Laura Up", "last_modified": 1707927044, "price_change_number": 22766324}, {"appid": 2684020, "name": "Grav1ty", "last_modified": 1710372253, "price_change_number": 0}, {"appid": 2684030, "name": "Happy Hour Hero", "last_modified": 1708116104, "price_change_number": 22513208}, {"appid": 2684070, "name": "Galaxy At War", "last_modified": 1709966889, "price_change_number": 0}, {"appid": 2684080, "name": "BattleTubers", "last_modified": 1703533041, "price_change_number": 0}, {"appid": 2684090, "name": "SPIN UP", "last_modified": 1704812336, "price_change_number": 22766324}, {"appid": 2684100, "name": "Real Time Attack", "last_modified": 1710222062, "price_change_number": 0}, {"appid": 2684120, "name": "Recon Quest", "last_modified": 1708475072, "price_change_number": 22736671}, {"appid": 2684130, "name": "Gravity Lab", "last_modified": 1705595866, "price_change_number": 0}, {"appid": 2684200, "name": "Splat Arena", "last_modified": 1700555877, "price_change_number": 22766324}, {"appid": 2684220, "name": "Heartwell", "last_modified": 1705862567, "price_change_number": 0}, {"appid": 2684230, "name": "Bubble Ball!", "last_modified": 1707781666, "price_change_number": 21761650}, {"appid": 2684240, "name": "Symbio", "last_modified": 1699429014, "price_change_number": 0}, {"appid": 2684260, "name": "VR Waifu - MuChan", "last_modified": 1705564680, "price_change_number": 22312985}, {"appid": 2684280, "name": "\u6c34\u7bb1", "last_modified": 1702786520, "price_change_number": 22766324}, {"appid": 2684290, "name": "Danger Drone", "last_modified": 1702489563, "price_change_number": 22766324}, {"appid": 2684300, "name": "Just skill shooter 2", "last_modified": 1710414047, "price_change_number": 22766324}, {"appid": 2684310, "name": "Dangerous FightCIA", "last_modified": 1710456959, "price_change_number": 22690818}, {"appid": 2684340, "name": "Happy Telepathy", "last_modified": 1705974273, "price_change_number": 0}, {"appid": 2684360, "name": "Planet Scanner", "last_modified": 1702065044, "price_change_number": 0}, {"appid": 2684370, "name": "Dinosaur World", "last_modified": 1703562522, "price_change_number": 0}, {"appid": 2684390, "name": "Fantasy Dungeon", "last_modified": 1710093246, "price_change_number": 0}, {"appid": 2684400, "name": "Just Keep Running", "last_modified": 1702301138, "price_change_number": 0}, {"appid": 2684410, "name": "\u661f\u9645\u5b64\u72fc", "last_modified": 1707816787, "price_change_number": 22766324}, {"appid": 2684420, "name": "BALL PIT KING 3D", "last_modified": 1702141826, "price_change_number": 22784101}, {"appid": 2684450, "name": "Buns: Bunny Survivor", "last_modified": 1703370152, "price_change_number": 22776506}, {"appid": 2684490, "name": "CrimeSceneCleaners\uff5c\u7279\u6b8a\u6e05\u6383", "last_modified": 1699771611, "price_change_number": 0}, {"appid": 2684500, "name": "Alpha League", "last_modified": 1709870080, "price_change_number": 22736671}, {"appid": 2684510, "name": "Cards of Divinity", "last_modified": 1709381685, "price_change_number": 0}, {"appid": 2684520, "name": "Conjury", "last_modified": 1704545815, "price_change_number": 22766324}, {"appid": 2684530, "name": "\u9ed1\u6697\u4e4b\u52032 \u524d\u4f20", "last_modified": 1701090313, "price_change_number": 21293034}, {"appid": 2684580, "name": "Elumin", "last_modified": 1709667390, "price_change_number": 0}, {"appid": 2684630, "name": "Endacopia", "last_modified": 1701891597, "price_change_number": 0}, {"appid": 2684650, "name": "CodeX", "last_modified": 1705423345, "price_change_number": 22626142}, {"appid": 2684720, "name": "They Are Hundreds: Prepped", "last_modified": 1702256089, "price_change_number": 22769417}, {"appid": 2684740, "name": "Traitor", "last_modified": 1699655782, "price_change_number": 0}, {"appid": 2684760, "name": "Evil Mountains", "last_modified": 1710270242, "price_change_number": 0}, {"appid": 2684780, "name": "Chromatic Isle", "last_modified": 1705327435, "price_change_number": 22736671}, {"appid": 2684790, "name": "William and Sly: Classic Collection", "last_modified": 1708713461, "price_change_number": 22736671}, {"appid": 2684800, "name": "Shaylushay Treasure Expedition", "last_modified": 1701262132, "price_change_number": 22766324}, {"appid": 2684840, "name": "Felbound", "last_modified": 1709119211, "price_change_number": 0}, {"appid": 2684850, "name": "MULTIPLAYER BOTS", "last_modified": 1700591527, "price_change_number": 22766324}, {"appid": 2684930, "name": "TRUFFLE", "last_modified": 1706257171, "price_change_number": 22736671}, {"appid": 2684940, "name": "The Piece", "last_modified": 1701302865, "price_change_number": 22139034}, {"appid": 2684950, "name": "Colorful Katana", "last_modified": 1704332433, "price_change_number": 0}, {"appid": 2685030, "name": "Drum Legend", "last_modified": 1701753089, "price_change_number": 22766324}, {"appid": 2685060, "name": "\u96f7\u5251\u4f20\u8bf4", "last_modified": 1706609771, "price_change_number": 22175245}, {"appid": 2685070, "name": "World War: Rome - Free Strategy Game", "last_modified": 1703743707, "price_change_number": 22736671}, {"appid": 2685090, "name": "Ufouria: The Saga 2", "last_modified": 1709132432, "price_change_number": 22544534}, {"appid": 2685150, "name": "Ace Racers SP", "last_modified": 1701398781, "price_change_number": 22736671}, {"appid": 2685160, "name": "Ball Coin Chapter 5", "last_modified": 1703889353, "price_change_number": 22736671}, {"appid": 2685170, "name": "Dice Battle", "last_modified": 1704136835, "price_change_number": 22104294}, {"appid": 2685180, "name": "Fresh Hell", "last_modified": 1706081755, "price_change_number": 0}, {"appid": 2685200, "name": "Where Christmas Elves \u5723\u8bde\u7cbe\u7075\u5728\u54ea\u91cc", "last_modified": 1703324333, "price_change_number": 22766324}, {"appid": 2685210, "name": "Where Jellyfish \u6c34\u6bcd\u5728\u54ea\u91cc", "last_modified": 1703555297, "price_change_number": 22736671}, {"appid": 2685220, "name": "Where Pandas \u718a\u732b\u5728\u54ea\u91cc", "last_modified": 1703324329, "price_change_number": 22766324}, {"appid": 2685230, "name": "Where Sacabamba Aspises \u8428\u5361\u73ed\u7532\u9c7c\u5728\u54ea\u91cc", "last_modified": 1703324327, "price_change_number": 22766324}, {"appid": 2685240, "name": "Where Cats \u732b\u54aa\u5728\u54ea\u91cc", "last_modified": 1703324324, "price_change_number": 22766324}, {"appid": 2685250, "name": "Where Rabbits \u5154\u5b50\u5728\u54ea\u91cc", "last_modified": 1703324322, "price_change_number": 22766324}, {"appid": 2685260, "name": "Where Ferrets \u96ea\u8c82\u5728\u54ea\u91cc", "last_modified": 1703297518, "price_change_number": 0}, {"appid": 2685300, "name": "RYBot", "last_modified": 1708985320, "price_change_number": 22626148}, {"appid": 2685320, "name": "One More Day", "last_modified": 1708971602, "price_change_number": 0}, {"appid": 2685330, "name": "Deathrun", "last_modified": 1699910370, "price_change_number": 22736671}, {"appid": 2685350, "name": "POOR ARTIFACT MAKER", "last_modified": 1707278912, "price_change_number": 0}, {"appid": 2685360, "name": "Remove: \ubc94\uc8c4\ub294 \ud754\uc801\uc744 \ub0a8\uae34\ub2e4", "last_modified": 1702640677, "price_change_number": 22736671}, {"appid": 2685370, "name": "Meowmunitions", "last_modified": 1707752367, "price_change_number": 0}, {"appid": 2685380, "name": "CHAIRS", "last_modified": 1708413973, "price_change_number": 0}, {"appid": 2685410, "name": "\u30b9\u30d4\u30c0\u30b9 SPEED-DEUS-EX-MACHINA", "last_modified": 1702281632, "price_change_number": 22736671}, {"appid": 2685420, "name": "TunsTan", "last_modified": 1708652502, "price_change_number": 0}, {"appid": 2685430, "name": "\u4e91\u5c9a\u4e5d\u6b4c", "last_modified": 1706849809, "price_change_number": 22736671}, {"appid": 2685450, "name": "Happy Color Links", "last_modified": 1701798481, "price_change_number": 0}, {"appid": 2685480, "name": "\u6642\u5de1\u308b\u5b9d\u77f3\u7cbe\u970a", "last_modified": 1700225843, "price_change_number": 0}, {"appid": 2685490, "name": "Detective Hayseed - The Cloning Madness", "last_modified": 1704272404, "price_change_number": 21501157}, {"appid": 2685520, "name": "To The Tavern", "last_modified": 1699644592, "price_change_number": 0}, {"appid": 2685550, "name": "Snaketris: Rescue 'em all", "last_modified": 1709925215, "price_change_number": 0}, {"appid": 2685570, "name": "Plus Ultra: Legado", "last_modified": 1703075023, "price_change_number": 0}, {"appid": 2685600, "name": "My Confounding Cat is Criminally Cute!", "last_modified": 1703105577, "price_change_number": 0}, {"appid": 2685610, "name": "Wanting Wings", "last_modified": 1702598478, "price_change_number": 22766324}, {"appid": 2685620, "name": "\u53cd\u8f6c21\u514b", "last_modified": 1709679308, "price_change_number": 22766324}, {"appid": 2685630, "name": "Sling Puzzle: Golf Master", "last_modified": 1708672685, "price_change_number": 22565295}, {"appid": 2685670, "name": "Lines On Sides", "last_modified": 1699688180, "price_change_number": 0}, {"appid": 2685760, "name": "Team Disorder", "last_modified": 1710396261, "price_change_number": 22766324}, {"appid": 2685770, "name": "Idle Progress", "last_modified": 1704482707, "price_change_number": 22736671}, {"appid": 2685780, "name": "Seven Little Spider Kittens", "last_modified": 1701010478, "price_change_number": 22766324}, {"appid": 2685810, "name": "Micro macro farm", "last_modified": 1703759899, "price_change_number": 22766324}, {"appid": 2685840, "name": "Pastel\u2606Parade", "last_modified": 1709950936, "price_change_number": 0}, {"appid": 2685850, "name": "Hoku Shrine", "last_modified": 1710335317, "price_change_number": 0}, {"appid": 2685900, "name": "Mind Over Magnet", "last_modified": 1707832623, "price_change_number": 0}, {"appid": 2686020, "name": "Faith in Despair", "last_modified": 1709892273, "price_change_number": 0}, {"appid": 2686040, "name": "Deadly Survival", "last_modified": 1700174117, "price_change_number": 0}, {"appid": 2686060, "name": "Candle Daemon", "last_modified": 1708641316, "price_change_number": 22462135}, {"appid": 2686080, "name": "Sad Satan", "last_modified": 1710407893, "price_change_number": 0}, {"appid": 2686110, "name": "UNHEIM", "last_modified": 1709653698, "price_change_number": 0}, {"appid": 2686120, "name": "Inka Aventura: Saga de Pachakutiq", "last_modified": 1704824499, "price_change_number": 0}, {"appid": 2686250, "name": "Morels: The Hunt 2", "last_modified": 1710117645, "price_change_number": 0}, {"appid": 2686290, "name": "Tamara In The Forsaken Dungeon", "last_modified": 1705763602, "price_change_number": 22766324}, {"appid": 2686320, "name": "Sexy Iron Maidens", "last_modified": 1708955846, "price_change_number": 0}, {"appid": 2686330, "name": "NOCLIP", "last_modified": 1709133317, "price_change_number": 22544763}, {"appid": 2686350, "name": "Home Defender", "last_modified": 1702745749, "price_change_number": 22513184}, {"appid": 2686360, "name": "Oh Darling! I Hate To Tell You This...", "last_modified": 1702907943, "price_change_number": 22736671}, {"appid": 2686480, "name": "Feline Shenanigans", "last_modified": 1706810506, "price_change_number": 22766324}, {"appid": 2686500, "name": "Please Leave Me Alone, I Need to Poop", "last_modified": 1710369705, "price_change_number": 0}, {"appid": 2686520, "name": "More Than Human", "last_modified": 1701308373, "price_change_number": 0}, {"appid": 2686570, "name": "Waltz and Jam", "last_modified": 1709204985, "price_change_number": 0}, {"appid": 2686580, "name": "Trinity Survivors", "last_modified": 1710401966, "price_change_number": 22766324}, {"appid": 2686590, "name": "Speak of the Devil I: A Deathly Proposition", "last_modified": 1702617052, "price_change_number": 22766324}, {"appid": 2686630, "name": "Voyagers of Nera", "last_modified": 1701881337, "price_change_number": 0}, {"appid": 2686640, "name": "The Mouse The Merrier", "last_modified": 1709862141, "price_change_number": 0}, {"appid": 2686670, "name": "Hide or Sex", "last_modified": 1702926754, "price_change_number": 22766324}, {"appid": 2686690, "name": "Suika Shapes", "last_modified": 1709353786, "price_change_number": 22766324}, {"appid": 2686720, "name": "\u5bbf\u4e3b\u30ac\u30fc\u30c9\u30de\u30f3 - Host Security Guard -", "last_modified": 1702522397, "price_change_number": 22766324}, {"appid": 2686740, "name": "Divergence", "last_modified": 1701703911, "price_change_number": 22736671}, {"appid": 2686750, "name": "Keep Up", "last_modified": 1705359673, "price_change_number": 22766324}, {"appid": 2686760, "name": "Criminal Behavior", "last_modified": 1710349778, "price_change_number": 22766324}, {"appid": 2686770, "name": "\u30c7\u30b8\u30d7\u30e9\u30b3\u30ec\u30af\u30b7\u30e7\u30f3 \u307e\u308b\u3054\u3068\u9244\u9053\uff01\u30df\u30cb \uff5eJR\u897f\u65e5\u672c\u7de8\uff5e", "last_modified": 1705646054, "price_change_number": 22766324}, {"appid": 2686780, "name": "G-MODE\u30a2\u30fc\u30ab\u30a4\u30d6\u30b9+ \u63a2\u5075\u30fb\u7678\u751f\u5ddd\u51cc\u4ecb\u4e8b\u4ef6\u8b5a Vol.13\u300c\u9ec4\u660f\u306f\u7460\u7483\u306e\u8ffd\u61b6\u300d", "last_modified": 1703118583, "price_change_number": 22766324}, {"appid": 2686790, "name": "G-MODE\u30a2\u30fc\u30ab\u30a4\u30d6\u30b9+ \u63a2\u5075\u30fb\u7678\u751f\u5ddd\u51cc\u4ecb\u4e8b\u4ef6\u8b5a Vol.14\u300c\u87ba\u65cb\u306e\u68fa\u6bba\u4eba\u4e8b\u4ef6\u300d", "last_modified": 1709773897, "price_change_number": 22663704}, {"appid": 2686810, "name": "Dimlight Dungeon", "last_modified": 1710033851, "price_change_number": 22736671}, {"appid": 2686820, "name": "isekizima: Ruins and Tails Journey", "last_modified": 1709717743, "price_change_number": 0}, {"appid": 2686850, "name": "Tochos vs. Brokens", "last_modified": 1705004107, "price_change_number": 22736671}, {"appid": 2686900, "name": "Churn Vector", "last_modified": 1705042807, "price_change_number": 22766324}, {"appid": 2686910, "name": "\u4efb\u4fa0", "last_modified": 1701324339, "price_change_number": 0}, {"appid": 2686920, "name": "Flagged Down", "last_modified": 1709415013, "price_change_number": 0}, {"appid": 2686930, "name": "Boo's There?", "last_modified": 1703793966, "price_change_number": 22736671}, {"appid": 2686950, "name": "Byte Hack", "last_modified": 1710213708, "price_change_number": 0}, {"appid": 2686960, "name": "Shatterbound", "last_modified": 1707361202, "price_change_number": 0}, {"appid": 2686980, "name": "Planet Suika", "last_modified": 1702773227, "price_change_number": 21506328}, {"appid": 2686990, "name": "The Maze Contract", "last_modified": 1701579579, "price_change_number": 21377411}, {"appid": 2687000, "name": "no sleep for sole", "last_modified": 1708112023, "price_change_number": 0}, {"appid": 2687040, "name": "9Cat Saga", "last_modified": 1709819327, "price_change_number": 0}, {"appid": 2687080, "name": "Gentle Female Boss \u6e29\u67d4\u5973\u4e0a\u53f8", "last_modified": 1701418707, "price_change_number": 22766324}, {"appid": 2687110, "name": "\u5f00\u5c40\u62bd\u53d6\u8d85\u7ea7\u5929\u8d4b", "last_modified": 1708085618, "price_change_number": 22736671}, {"appid": 2687130, "name": "Aculeata", "last_modified": 1703853922, "price_change_number": 21776149}, {"appid": 2687140, "name": "\u5f02\u5883\u8ff7\u9014 Epic of Tarot", "last_modified": 1705474412, "price_change_number": 22736671}, {"appid": 2687160, "name": "Notanote", "last_modified": 1707880683, "price_change_number": 22736671}, {"appid": 2687190, "name": "100 Christmas Cats", "last_modified": 1705737487, "price_change_number": 22736671}, {"appid": 2687200, "name": "100 London Cats", "last_modified": 1707375994, "price_change_number": 22736671}, {"appid": 2687220, "name": "Drops of God: Creating your Ambrosia", "last_modified": 1710231150, "price_change_number": 0}, {"appid": 2687300, "name": "Aarik And The Ruined Kingdom", "last_modified": 1709940846, "price_change_number": 0}, {"appid": 2687320, "name": "KOSMOS: The Discovery of Nature", "last_modified": 1699610315, "price_change_number": 0}, {"appid": 2687410, "name": "\u30e9\u30a4\u30d6\u30d4\u30af\u30c8", "last_modified": 1703252596, "price_change_number": 22736671}, {"appid": 2687470, "name": "Code of Desire", "last_modified": 1703207526, "price_change_number": 0}, {"appid": 2687490, "name": "Super Drunken Guy", "last_modified": 1709740693, "price_change_number": 0}, {"appid": 2687500, "name": "Tails of War", "last_modified": 1706299780, "price_change_number": 22736671}, {"appid": 2687510, "name": "Centrist", "last_modified": 1708609717, "price_change_number": 22766324}, {"appid": 2687530, "name": "Fairy Carrots", "last_modified": 1704922806, "price_change_number": 21935635}, {"appid": 2687540, "name": "Gateway to the Kulikovo Field: The Battle of Yepifan", "last_modified": 1701350788, "price_change_number": 22736671}, {"appid": 2687590, "name": "Sanctuary in Time", "last_modified": 1703706712, "price_change_number": 22103445}, {"appid": 2687600, "name": "Doppelg\u00e4nger", "last_modified": 1709183210, "price_change_number": 21640169}, {"appid": 2687610, "name": "Walrus Run", "last_modified": 1709914215, "price_change_number": 0}, {"appid": 2687650, "name": "Y2K Directive", "last_modified": 1709821405, "price_change_number": 0}, {"appid": 2687680, "name": "Barrhell", "last_modified": 1706034029, "price_change_number": 0}, {"appid": 2687690, "name": "Stranded On An Island", "last_modified": 1707405148, "price_change_number": 0}, {"appid": 2687700, "name": "Lost in Dread", "last_modified": 1704366946, "price_change_number": 0}, {"appid": 2687820, "name": "StoicScape", "last_modified": 1706622252, "price_change_number": 22231175}, {"appid": 2687850, "name": "AWA 2024", "last_modified": 1702409557, "price_change_number": 22766324}, {"appid": 2687940, "name": "Slot Shots Pinball Ultimate Edition", "last_modified": 1710514348, "price_change_number": 22766324}, {"appid": 2687950, "name": "Shattered Kingdoms", "last_modified": 1704147330, "price_change_number": 22736671}, {"appid": 2687960, "name": "Desolate City: Last Show", "last_modified": 1710156009, "price_change_number": 0}, {"appid": 2687970, "name": "TRIBES 3: Rivals", "last_modified": 1710365933, "price_change_number": 22734609}, {"appid": 2687990, "name": "The Black Guards of Odom - Desert Town Prison", "last_modified": 1710488332, "price_change_number": 22766324}, {"appid": 2688000, "name": "Jump, Froggy! Jump!", "last_modified": 1705354693, "price_change_number": 22002822}, {"appid": 2688010, "name": "TRETIS", "last_modified": 1700814784, "price_change_number": 0}, {"appid": 2688030, "name": "Serve The Cups", "last_modified": 1699632110, "price_change_number": 0}, {"appid": 2688100, "name": "Token Town", "last_modified": 1702446128, "price_change_number": 22659360}, {"appid": 2688110, "name": "The Wizard Party", "last_modified": 1709618886, "price_change_number": 0}, {"appid": 2688140, "name": "Amidst The Haze", "last_modified": 1707635371, "price_change_number": 22766324}, {"appid": 2688180, "name": "Hyperfield", "last_modified": 1709204353, "price_change_number": 22675684}, {"appid": 2688210, "name": "Ukraine War 2022", "last_modified": 1709118647, "price_change_number": 22659394}, {"appid": 2688370, "name": "Scavenger vr", "last_modified": 1701908700, "price_change_number": 22766324}, {"appid": 2688390, "name": "\u4eca\u3001\u79c1\u305f\u3061\u306e\u5b66\u6821\u306f...", "last_modified": 1701270046, "price_change_number": 21427417}, {"appid": 2688400, "name": "You Draw, I Guess", "last_modified": 1709615284, "price_change_number": 22766324}, {"appid": 2688410, "name": "Tales From the Herd", "last_modified": 1710257918, "price_change_number": 0}, {"appid": 2688440, "name": "Fimbul's Gemboree", "last_modified": 1701909270, "price_change_number": 22736671}, {"appid": 2688480, "name": "StarWinds", "last_modified": 1700015408, "price_change_number": 0}, {"appid": 2688520, "name": "Hrumka", "last_modified": 1700726148, "price_change_number": 0}, {"appid": 2688530, "name": "Rank \u00b7 Boss \u00b7 Bullets", "last_modified": 1702437566, "price_change_number": 21487002}, {"appid": 2688570, "name": "The Inn-Sanity", "last_modified": 1710352614, "price_change_number": 0}, {"appid": 2688600, "name": "Descent from Arkov's tower Prologue", "last_modified": 1710434323, "price_change_number": 22736671}, {"appid": 2688610, "name": "Forgotten Knight", "last_modified": 1701426006, "price_change_number": 22736671}, {"appid": 2688620, "name": "Temporarily", "last_modified": 1704253316, "price_change_number": 21740484}, {"appid": 2688650, "name": "\u5b8c\u7f8e\u7d30\u80de\u8a08\u756b", "last_modified": 1710482450, "price_change_number": 0}, {"appid": 2688680, "name": "\u9b54\u5854\u5c11\u5973", "last_modified": 1710128173, "price_change_number": 22585547}, {"appid": 2688720, "name": "Hidden Cats: Magic Forest", "last_modified": 1704914326, "price_change_number": 22766324}, {"appid": 2688730, "name": "Reckless Rally", "last_modified": 1702641041, "price_change_number": 22736671}, {"appid": 2688780, "name": "Don't Be Sus", "last_modified": 1704197106, "price_change_number": 0}, {"appid": 2688790, "name": "Happy Wonderland Solitaire", "last_modified": 1701362855, "price_change_number": 22766324}, {"appid": 2688890, "name": "UFO: Henfield", "last_modified": 1706188124, "price_change_number": 22766324}, {"appid": 2688900, "name": "Super Algebrawl", "last_modified": 1707761509, "price_change_number": 22766324}, {"appid": 2688930, "name": "Legend of Egypt - Jewels of the Gods", "last_modified": 1700920637, "price_change_number": 22766324}, {"appid": 2688940, "name": "Buzz Cut Simulation", "last_modified": 1701353620, "price_change_number": 21444061}, {"appid": 2688960, "name": "Eternity's Echo: Patient Zero", "last_modified": 1708123001, "price_change_number": 0}, {"appid": 2688980, "name": "The World Has Gone", "last_modified": 1710343762, "price_change_number": 0}, {"appid": 2689060, "name": "Nordland Mahjongg", "last_modified": 1700920630, "price_change_number": 22766324}, {"appid": 2689120, "name": "Gladio Mori", "last_modified": 1703697841, "price_change_number": 0}, {"appid": 2689130, "name": "CipherCraft: Cyber Guardian Introduction", "last_modified": 1708706719, "price_change_number": 22736671}, {"appid": 2689200, "name": "SKUF SIMULATOR", "last_modified": 1709625979, "price_change_number": 0}, {"appid": 2689220, "name": "No Worries", "last_modified": 1705560155, "price_change_number": 21943407}, {"appid": 2689230, "name": "FURRY BACKROOMS", "last_modified": 1708702829, "price_change_number": 0}, {"appid": 2689400, "name": "It's All Connected", "last_modified": 1705387230, "price_change_number": 0}, {"appid": 2689420, "name": "Breekha", "last_modified": 1701505302, "price_change_number": 0}, {"appid": 2689440, "name": "\u7834\u6653\u65f6\u5206\u7684\u4e66\u4fe1-\u671d\u95fb\u7bc7-", "last_modified": 1702917607, "price_change_number": 0}, {"appid": 2689470, "name": "CRUEL", "last_modified": 1703103997, "price_change_number": 0}, {"appid": 2689480, "name": "Christmas Wonderland 14 Collector's Edition", "last_modified": 1702544646, "price_change_number": 21533839}, {"appid": 2689490, "name": "phantom unit 999", "last_modified": 1704313042, "price_change_number": 22503157}, {"appid": 2689500, "name": "FishVerse - Ultimate Fishing", "last_modified": 1705055396, "price_change_number": 22736671}, {"appid": 2689540, "name": "Elemental Ascent", "last_modified": 1699991565, "price_change_number": 0}, {"appid": 2689590, "name": "\u661f\u57df\u5546\u65c5", "last_modified": 1704624498, "price_change_number": 0}, {"appid": 2689600, "name": "SOS Zombie Survivors", "last_modified": 1701194877, "price_change_number": 22766324}, {"appid": 2689610, "name": "Trust No One", "last_modified": 1710433946, "price_change_number": 0}, {"appid": 2689630, "name": "Eternal Spring VR", "last_modified": 1709671332, "price_change_number": 22736671}, {"appid": 2689640, "name": "Super Cube 3D", "last_modified": 1705352335, "price_change_number": 22766324}, {"appid": 2689710, "name": "Emerald Caravan", "last_modified": 1702287691, "price_change_number": 0}, {"appid": 2689820, "name": "The Death Focal", "last_modified": 1707641410, "price_change_number": 22766324}, {"appid": 2689850, "name": "\uff13\u3064\u306e\u7121\u7aae\u52d5 -Trois Mouvements perp\u00e9tuels-", "last_modified": 1706665220, "price_change_number": 22231183}, {"appid": 2689870, "name": "Rekindling The Flame", "last_modified": 1702259176, "price_change_number": 22736671}, {"appid": 2689880, "name": "Cyber Story", "last_modified": 1710158226, "price_change_number": 22736671}, {"appid": 2689910, "name": "Rivals' Duel", "last_modified": 1706460049, "price_change_number": 22736671}, {"appid": 2689930, "name": "Detective Instinct: Farewell, My Beloved", "last_modified": 1700928080, "price_change_number": 0}, {"appid": 2689950, "name": "grave desecrator", "last_modified": 1701492709, "price_change_number": 0}, {"appid": 2689960, "name": "Rocket Engineer", "last_modified": 1709239856, "price_change_number": 0}, {"appid": 2690020, "name": "King of Throwing", "last_modified": 1701739743, "price_change_number": 21399629}, {"appid": 2690050, "name": "ORB IN WONDER", "last_modified": 1701531895, "price_change_number": 22002814}, {"appid": 2690080, "name": "Watson", "last_modified": 1700014813, "price_change_number": 0}, {"appid": 2690090, "name": "Seven Second Summer Camp", "last_modified": 1702682645, "price_change_number": 0}, {"appid": 2690110, "name": "Waiting in the Lime forest", "last_modified": 1700579344, "price_change_number": 0}, {"appid": 2690150, "name": "Molten Winds: Open Editon", "last_modified": 1706347517, "price_change_number": 22736671}, {"appid": 2690160, "name": "\u4e09\u56fd\uff1a\u6211\u662f\u4e3b\u516c", "last_modified": 1703581123, "price_change_number": 22736671}, {"appid": 2690170, "name": "\u5de6\u7f8e\u4eba\u53f3\u4f73\u4e3d / A group of beauties surrounded me", "last_modified": 1703755241, "price_change_number": 22766324}, {"appid": 2690180, "name": "\u897f\u6c5f\u8239\u5382", "last_modified": 1710470160, "price_change_number": 22766324}, {"appid": 2690190, "name": "shaiya", "last_modified": 1708666701, "price_change_number": 22736671}, {"appid": 2690250, "name": "Back To School", "last_modified": 1709175356, "price_change_number": 22736671}, {"appid": 2690290, "name": "24H Stories: The Blackout", "last_modified": 1701086541, "price_change_number": 21289836}, {"appid": 2690570, "name": "Sprite Wars", "last_modified": 1708763578, "price_change_number": 22602466}, {"appid": 2690580, "name": "Luminaria: Dark Echoes", "last_modified": 1709039003, "price_change_number": 22766324}, {"appid": 2690610, "name": "XELAN FORCE", "last_modified": 1707889263, "price_change_number": 22335862}, {"appid": 2690630, "name": "AI.Gears : Team Tag Battle", "last_modified": 1701333218, "price_change_number": 21338994}, {"appid": 2690680, "name": "What games does your dad play - \u4f60\u8001\u8c46\u73a9\u4e5cGAME", "last_modified": 1702819930, "price_change_number": 22766324}, {"appid": 2690700, "name": "Golden Rails: Harvest of Riddles", "last_modified": 1704785240, "price_change_number": 22766324}, {"appid": 2690770, "name": "Grandfather Simulator", "last_modified": 1701946487, "price_change_number": 22766324}, {"appid": 2690780, "name": "Mad Jyacer", "last_modified": 1700939317, "price_change_number": 22766324}, {"appid": 2690790, "name": "Christmas Present", "last_modified": 1704570282, "price_change_number": 22766324}, {"appid": 2690800, "name": "Sex Simulator - Vampires", "last_modified": 1701162598, "price_change_number": 22766324}, {"appid": 2690810, "name": "Hidden Object Secrets: Family Revenge Collector's Edition", "last_modified": 1701668722, "price_change_number": 22766324}, {"appid": 2690820, "name": "Hidden Object Legends: Deadly Love Collector's Edition", "last_modified": 1703495827, "price_change_number": 22766324}, {"appid": 2690830, "name": "Unrivaled Heroes: 2.5D Brawler", "last_modified": 1709856143, "price_change_number": 0}, {"appid": 2690870, "name": "Rogue Realms", "last_modified": 1709911703, "price_change_number": 0}, {"appid": 2690890, "name": "Trivia Crack World", "last_modified": 1709913520, "price_change_number": 0}, {"appid": 2690900, "name": "Time Machine Bronzeville", "last_modified": 1706552996, "price_change_number": 22766324}, {"appid": 2690950, "name": "CHUSHPAN", "last_modified": 1710524196, "price_change_number": 0}, {"appid": 2690960, "name": "Piece Link", "last_modified": 1710165404, "price_change_number": 22717164}, {"appid": 2690970, "name": "\u5783\u573e\u6876\u519b\u56e2", "last_modified": 1706175872, "price_change_number": 22736671}, {"appid": 2690980, "name": "Fire Guardian", "last_modified": 1703680384, "price_change_number": 22766324}, {"appid": 2691010, "name": "Assembly Line 2 Mobile Version", "last_modified": 1701363320, "price_change_number": 22766324}, {"appid": 2691050, "name": "Neongarten", "last_modified": 1705581515, "price_change_number": 0}, {"appid": 2691070, "name": "KILL AI", "last_modified": 1706874286, "price_change_number": 22766324}, {"appid": 2691200, "name": "Tiny Car Mess", "last_modified": 1704112261, "price_change_number": 22766324}, {"appid": 2691220, "name": "Ara Ara Auntie Incest", "last_modified": 1705692894, "price_change_number": 22766324}, {"appid": 2691240, "name": "Joe is not lost - Jigsaw Landscapes", "last_modified": 1709642698, "price_change_number": 0}, {"appid": 2691250, "name": "Unreal Kingdoms", "last_modified": 1702010430, "price_change_number": 22736671}, {"appid": 2691280, "name": "Corpse Master Carnage", "last_modified": 1703097916, "price_change_number": 21444030}, {"appid": 2691340, "name": "The Christopher Redemption - I", "last_modified": 1700056065, "price_change_number": 0}, {"appid": 2691350, "name": ".Forty-Five", "last_modified": 1709908949, "price_change_number": 22736671}, {"appid": 2691360, "name": "Deckbuilder Fantasy", "last_modified": 1709628588, "price_change_number": 22736671}, {"appid": 2691390, "name": "Smoking Simulator", "last_modified": 1701443444, "price_change_number": 22766324}, {"appid": 2691410, "name": "Gossip & Potions: Tales from the Witch Shop", "last_modified": 1700629150, "price_change_number": 0}, {"appid": 2691420, "name": "Magic Labyrinth 3D", "last_modified": 1702920356, "price_change_number": 22766324}, {"appid": 2691430, "name": "Champions", "last_modified": 1702395955, "price_change_number": 21504433}, {"appid": 2691450, "name": "Giant Hornet", "last_modified": 1708787039, "price_change_number": 0}, {"appid": 2691470, "name": "Lisa Total investigation!", "last_modified": 1708714811, "price_change_number": 22690821}, {"appid": 2691490, "name": "Hypothetimania", "last_modified": 1709163037, "price_change_number": 0}, {"appid": 2691510, "name": "Rhythm Station", "last_modified": 1709832642, "price_change_number": 0}, {"appid": 2691550, "name": "Parisyte", "last_modified": 1705384644, "price_change_number": 0}, {"appid": 2691560, "name": "Dark is the Void", "last_modified": 1707256841, "price_change_number": 22231171}, {"appid": 2691580, "name": "Space Garbage", "last_modified": 1707230058, "price_change_number": 22328570}, {"appid": 2691600, "name": "Unwelcome", "last_modified": 1704765206, "price_change_number": 0}, {"appid": 2691700, "name": "28 Babes Later", "last_modified": 1703197902, "price_change_number": 21634375}, {"appid": 2691750, "name": "Beast Collector", "last_modified": 1701310463, "price_change_number": 22736671}, {"appid": 2691760, "name": "The Chronicles of Ezra Blackwell: Episode 1, Pappi's Peril", "last_modified": 1709395491, "price_change_number": 21989504}, {"appid": 2691780, "name": "Reports from Vera Cruz", "last_modified": 1710526513, "price_change_number": 0}, {"appid": 2691790, "name": "Bubble Chicken Farm", "last_modified": 1709751435, "price_change_number": 0}, {"appid": 2691800, "name": "Luster Beasts", "last_modified": 1702021267, "price_change_number": 21452130}, {"appid": 2691830, "name": "ASTRA", "last_modified": 1708278440, "price_change_number": 22766324}, {"appid": 2691890, "name": "\u9010\u9e7f\u6218\u68cb", "last_modified": 1710213066, "price_change_number": 0}, {"appid": 2691900, "name": "The Little Witch and The Lost Memories", "last_modified": 1710440249, "price_change_number": 0}, {"appid": 2691960, "name": "Cardboard Battle Tanks: Desk Division", "last_modified": 1709218741, "price_change_number": 0}, {"appid": 2691980, "name": "System Override", "last_modified": 1701830993, "price_change_number": 22736671}, {"appid": 2692010, "name": "Five Nights at Backrooms: Waifu Edition", "last_modified": 1702094973, "price_change_number": 22766324}, {"appid": 2692030, "name": "Valkyrie Squad: Siege Breakers", "last_modified": 1709713838, "price_change_number": 0}, {"appid": 2692040, "name": "ThroneForge - The Fortress War", "last_modified": 1709540053, "price_change_number": 22766324}, {"appid": 2692160, "name": "BreadAttack", "last_modified": 1700734521, "price_change_number": 0}, {"appid": 2692210, "name": "DALDZAH", "last_modified": 1707318650, "price_change_number": 22736671}, {"appid": 2692270, "name": "Bird of Paradise", "last_modified": 1707924430, "price_change_number": 0}, {"appid": 2692280, "name": "My Ex-Future Family Season 2", "last_modified": 1700404667, "price_change_number": 0}, {"appid": 2692300, "name": "Cyber Horny", "last_modified": 1701534856, "price_change_number": 22766324}, {"appid": 2692350, "name": "1 FALSE MOVE", "last_modified": 1707170731, "price_change_number": 0}, {"appid": 2692360, "name": "\u3046\u3063\u304b\u308a\u5a5a\uff5e\u76ee\u899a\u3081\u305f\u3089\u3001\u30ef\u30b1\u3042\u308a\u4e0a\u53f8\u306e\u59bb\u3067\u3057\u305f\uff5e", "last_modified": 1706160870, "price_change_number": 22041607}, {"appid": 2692390, "name": "My Girls\u2019 Secrets", "last_modified": 1709862600, "price_change_number": 22766324}, {"appid": 2692430, "name": "Historical Fashion Dress Up", "last_modified": 1709887829, "price_change_number": 0}, {"appid": 2692440, "name": "LoveCraft", "last_modified": 1705689267, "price_change_number": 22736671}, {"appid": 2692450, "name": "Kurofune : Descobrimentos Portugueses", "last_modified": 1709136030, "price_change_number": 22736671}, {"appid": 2692460, "name": "Escape the super nerdy dungeon- W100 MASTER EDITION", "last_modified": 1702092722, "price_change_number": 0}, {"appid": 2692570, "name": "Sonder", "last_modified": 1709134067, "price_change_number": 22736671}, {"appid": 2692580, "name": "Scary Mine VR", "last_modified": 1702908168, "price_change_number": 21584569}, {"appid": 2692600, "name": "Abondoned village", "last_modified": 1700260970, "price_change_number": 0}, {"appid": 2692610, "name": "Sunny Beach Girls", "last_modified": 1708450188, "price_change_number": 22530214}, {"appid": 2692620, "name": "Hazard Pay", "last_modified": 1708695207, "price_change_number": 0}, {"appid": 2692640, "name": "Room", "last_modified": 1702487121, "price_change_number": 22766324}, {"appid": 2692650, "name": "Happy Horny Hell", "last_modified": 1708145121, "price_change_number": 0}, {"appid": 2692720, "name": "OG Puzzlers: Kira Maus", "last_modified": 1701773940, "price_change_number": 22766324}, {"appid": 2692740, "name": "Swappy World", "last_modified": 1710155179, "price_change_number": 0}, {"appid": 2692750, "name": "Epic of Brave", "last_modified": 1710089970, "price_change_number": 0}, {"appid": 2692760, "name": "ReHarmony", "last_modified": 1701709814, "price_change_number": 22766324}, {"appid": 2692800, "name": "I Love You Freddy", "last_modified": 1705855720, "price_change_number": 22766324}, {"appid": 2692860, "name": "Tickle Magnet", "last_modified": 1710478086, "price_change_number": 22774868}, {"appid": 2692890, "name": "Castle of Lord Velimir", "last_modified": 1706990917, "price_change_number": 0}, {"appid": 2692950, "name": "\u6b22\u8fce\u6765\u5230\u9ec4\u91d1\u4e4b\u661f\uff01Welcome to Planet E1d0r4d0!", "last_modified": 1707795114, "price_change_number": 0}, {"appid": 2692960, "name": "Void Guard", "last_modified": 1701442781, "price_change_number": 22736671}, {"appid": 2693060, "name": "Garten of Banban 7", "last_modified": 1708180181, "price_change_number": 0}, {"appid": 2693070, "name": "WARPZONE DRIFTER 2", "last_modified": 1701198582, "price_change_number": 22766324}, {"appid": 2693130, "name": "Treachery", "last_modified": 1700292997, "price_change_number": 0}, {"appid": 2693160, "name": "\u8d5b\u535a\u64a4\u9501", "last_modified": 1706235218, "price_change_number": 22626142}, {"appid": 2693200, "name": "Shadow Strike: Street Combat", "last_modified": 1701975718, "price_change_number": 22766324}, {"appid": 2693210, "name": "Hentai Tales: Sex Parlor Report", "last_modified": 1709874761, "price_change_number": 22682234}, {"appid": 2693240, "name": "Moratorium: Don\u2019t Beat This Game", "last_modified": 1708871650, "price_change_number": 22736671}, {"appid": 2693250, "name": "Way Nd Choice", "last_modified": 1710410460, "price_change_number": 0}, {"appid": 2693260, "name": "We Are SUP", "last_modified": 1707109637, "price_change_number": 0}, {"appid": 2693310, "name": "Harvest Knight", "last_modified": 1709906696, "price_change_number": 0}, {"appid": 2693320, "name": "Emerging Tactical", "last_modified": 1702326429, "price_change_number": 21491344}, {"appid": 2693340, "name": "DARK FOREST", "last_modified": 1703061659, "price_change_number": 21709588}, {"appid": 2693350, "name": "\u5077\u5916\u5356\u6a21\u62df\u5668\uff08\u6211\u57282083\u5e74\u7684\u672b\u4e16\u6c42\u751f\uff09", "last_modified": 1706014595, "price_change_number": 22775077}, {"appid": 2693360, "name": "Probot Soccer", "last_modified": 1702186940, "price_change_number": 21998151}, {"appid": 2693370, "name": "Dungeon of Despair", "last_modified": 1707668166, "price_change_number": 0}, {"appid": 2693380, "name": "Survival Mission Z", "last_modified": 1710551136, "price_change_number": 0}, {"appid": 2693400, "name": "Narava RPG", "last_modified": 1700496600, "price_change_number": 22736671}, {"appid": 2693410, "name": "The Reason for Your Smile", "last_modified": 1710133709, "price_change_number": 0}, {"appid": 2693450, "name": "Not Burned Evil", "last_modified": 1701505820, "price_change_number": 22766324}, {"appid": 2693460, "name": "Christmas Nightmare", "last_modified": 1701701998, "price_change_number": 22766324}, {"appid": 2693470, "name": "Journey To The Wand", "last_modified": 1706608862, "price_change_number": 22766324}, {"appid": 2693480, "name": "Color Splash: Animals", "last_modified": 1702040670, "price_change_number": 22785029}, {"appid": 2693530, "name": "Witching Stone", "last_modified": 1710499091, "price_change_number": 0}, {"appid": 2693650, "name": "Kill Invaders", "last_modified": 1709143903, "price_change_number": 22729312}, {"appid": 2693660, "name": "Radiant Bricks", "last_modified": 1706227705, "price_change_number": 0}, {"appid": 2693680, "name": "Slam Dunk Basketball", "last_modified": 1702669311, "price_change_number": 22766324}, {"appid": 2693700, "name": "Jewel Craft Fusion", "last_modified": 1701540412, "price_change_number": 22766324}, {"appid": 2693710, "name": "HARDCODED", "last_modified": 1709873920, "price_change_number": 0}, {"appid": 2693730, "name": "Dawnsbury Days", "last_modified": 1709910217, "price_change_number": 22785049}, {"appid": 2693810, "name": "Galaxy Trek", "last_modified": 1704122874, "price_change_number": 22766324}, {"appid": 2693820, "name": "Project N.E.X.T", "last_modified": 1703481185, "price_change_number": 22736671}, {"appid": 2693830, "name": "Panda Magix : Golden Trains Edition - Slots", "last_modified": 1701169049, "price_change_number": 21621332}, {"appid": 2693840, "name": "Choc N Roll", "last_modified": 1707933082, "price_change_number": 22766324}, {"appid": 2693890, "name": "Tales From Aturian - Battle of Cleaved Fields", "last_modified": 1702298916, "price_change_number": 21485601}, {"appid": 2693900, "name": "Henry's Escape: Prison", "last_modified": 1705978290, "price_change_number": 21747706}, {"appid": 2693920, "name": "Catting Over It", "last_modified": 1709023555, "price_change_number": 0}, {"appid": 2693930, "name": "Dice & Fold", "last_modified": 1705929762, "price_change_number": 0}, {"appid": 2693940, "name": "NeoDuel: Backpack Monsters", "last_modified": 1709498432, "price_change_number": 0}, {"appid": 2693950, "name": "Rifted Worlds", "last_modified": 1702526269, "price_change_number": 0}, {"appid": 2693960, "name": "Void Gore", "last_modified": 1709287250, "price_change_number": 22690854}, {"appid": 2694000, "name": "ANCIENT RUS VS LIZARDS", "last_modified": 1706383667, "price_change_number": 22766324}, {"appid": 2694020, "name": "Starbreed", "last_modified": 1703230621, "price_change_number": 0}, {"appid": 2694140, "name": "Zooplop", "last_modified": 1702847447, "price_change_number": 22766324}, {"appid": 2694150, "name": "Deficiency", "last_modified": 1700997002, "price_change_number": 0}, {"appid": 2694200, "name": "Skybase", "last_modified": 1708416967, "price_change_number": 0}, {"appid": 2694210, "name": "Exiled Survivors", "last_modified": 1708448551, "price_change_number": 22426865}, {"appid": 2694220, "name": "Quizz", "last_modified": 1707846358, "price_change_number": 22766324}, {"appid": 2694230, "name": "Shinobi Saga", "last_modified": 1709859844, "price_change_number": 0}, {"appid": 2694260, "name": "PIZZDILE", "last_modified": 1701114692, "price_change_number": 0}, {"appid": 2694290, "name": "Kill the Reaper", "last_modified": 1700176329, "price_change_number": 0}, {"appid": 2694330, "name": "My House and I Got Transported To Another World", "last_modified": 1701402022, "price_change_number": 0}, {"appid": 2694360, "name": "Twistingo: Hummingbird Haven Collector's Edition", "last_modified": 1701703013, "price_change_number": 21918539}, {"appid": 2694380, "name": "The First Present", "last_modified": 1703091598, "price_change_number": 21617731}, {"appid": 2694390, "name": "Synthwave Runner", "last_modified": 1701709311, "price_change_number": 22766324}, {"appid": 2694410, "name": "MDF Magical Defense Force Chapters 10-18", "last_modified": 1703961384, "price_change_number": 22766324}, {"appid": 2694440, "name": "Hentai Girls Slide", "last_modified": 1706894354, "price_change_number": 22766324}, {"appid": 2694460, "name": "The Quantum Conflict", "last_modified": 1708796762, "price_change_number": 0}, {"appid": 2694480, "name": "Sugar Fruits", "last_modified": 1701260161, "price_change_number": 22766324}, {"appid": 2694490, "name": "Path of Exile 2", "last_modified": 1709777135, "price_change_number": 22736671}, {"appid": 2694510, "name": "AMAERO : Gentle Guidance For A Virgin Boy", "last_modified": 1707465702, "price_change_number": 22766324}, {"appid": 2694520, "name": "Gallery of Things: Reveries", "last_modified": 1703205671, "price_change_number": 22766324}, {"appid": 2694530, "name": "The Cat", "last_modified": 1707064327, "price_change_number": 0}, {"appid": 2694600, "name": "My MILF Stepmom 2: Family Party\ud83d\udc8b", "last_modified": 1707356601, "price_change_number": 0}, {"appid": 2694620, "name": "Slay the Dungeon", "last_modified": 1708960612, "price_change_number": 0}, {"appid": 2694700, "name": "Bright Oak", "last_modified": 1700177204, "price_change_number": 0}, {"appid": 2694720, "name": "Moo Moo - Liar's Dice", "last_modified": 1708939377, "price_change_number": 22736671}, {"appid": 2694730, "name": "Samurai`s Way", "last_modified": 1708464442, "price_change_number": 22420917}, {"appid": 2694750, "name": "Married Woman Hypnosis Counseling", "last_modified": 1707466976, "price_change_number": 22766324}, {"appid": 2694770, "name": "Erotic Photoshoot", "last_modified": 1710212310, "price_change_number": 0}, {"appid": 2694800, "name": "\u6218\u6597\u5e73\u53f0", "last_modified": 1705072657, "price_change_number": 0}, {"appid": 2694860, "name": "Professional Married Woman Cuckolder", "last_modified": 1707466918, "price_change_number": 22766324}, {"appid": 2694890, "name": "ANNIHILATOR", "last_modified": 1701688259, "price_change_number": 21389365}, {"appid": 2694900, "name": "PEPITA VIAJERA ARCTIC", "last_modified": 1709126467, "price_change_number": 22736671}, {"appid": 2694920, "name": "Man in the Dark", "last_modified": 1709879235, "price_change_number": 22766324}, {"appid": 2694970, "name": "A Tale of Hard Nipples ~The secret to this town's confectionery's delicious sweets is rich, fresh milk~", "last_modified": 1705651302, "price_change_number": 22766324}, {"appid": 2695020, "name": "Magnavody", "last_modified": 1701771717, "price_change_number": 21404639}, {"appid": 2695030, "name": "TutoringNTR!? Having sex with the neighbor's total affirmation sister\u2026!", "last_modified": 1710488424, "price_change_number": 22766324}, {"appid": 2695040, "name": "The girl I like lost her virginity in the sex club NTR with me!?", "last_modified": 1710487300, "price_change_number": 22766324}, {"appid": 2695080, "name": "Purrfectly Hidden Cats - Kittenbay", "last_modified": 1708084258, "price_change_number": 22766324}, {"appid": 2695100, "name": "Gold Knight", "last_modified": 1709751687, "price_change_number": 0}, {"appid": 2695110, "name": "Infinite Forest Idle", "last_modified": 1707557722, "price_change_number": 22736671}, {"appid": 2695160, "name": "Phantom Girls: Ghostbuster", "last_modified": 1703154496, "price_change_number": 22766324}, {"appid": 2695210, "name": "Five-Star: Chef Ops", "last_modified": 1704975848, "price_change_number": 0}, {"appid": 2695230, "name": "Barbarians & Beasts", "last_modified": 1702061243, "price_change_number": 22766324}, {"appid": 2695240, "name": "Master Manager", "last_modified": 1705320751, "price_change_number": 22766324}, {"appid": 2695250, "name": "Fire Racing", "last_modified": 1704088376, "price_change_number": 21723437}, {"appid": 2695260, "name": "The Crimson Maid", "last_modified": 1701865552, "price_change_number": 0}, {"appid": 2695270, "name": "Miss Neko: Pirates", "last_modified": 1709045373, "price_change_number": 0}, {"appid": 2695290, "name": "EmyLiveShow: Dragon & Mistresses Tale", "last_modified": 1710518590, "price_change_number": 0}, {"appid": 2695400, "name": "Chaos Adventure", "last_modified": 1710469845, "price_change_number": 0}, {"appid": 2695420, "name": "Protecto", "last_modified": 1704443861, "price_change_number": 22766324}, {"appid": 2695450, "name": "Arcane Blood: The Shattered Star", "last_modified": 1702351545, "price_change_number": 22766324}, {"appid": 2695480, "name": "Chasm Crawl", "last_modified": 1710248035, "price_change_number": 0}, {"appid": 2695490, "name": "Age of Water", "last_modified": 1709151787, "price_change_number": 0}, {"appid": 2695590, "name": "Origin of Storms", "last_modified": 1700180875, "price_change_number": 0}, {"appid": 2695600, "name": "Hannah VCR", "last_modified": 1707330384, "price_change_number": 0}, {"appid": 2695710, "name": "God For A Day", "last_modified": 1709017560, "price_change_number": 0}, {"appid": 2695720, "name": "Hero Society", "last_modified": 1707454766, "price_change_number": 0}, {"appid": 2695730, "name": "Sofi Origins", "last_modified": 1702620397, "price_change_number": 22766324}, {"appid": 2695780, "name": "With Shining Eyes", "last_modified": 1710108985, "price_change_number": 22736671}, {"appid": 2695800, "name": "Dark And Evil", "last_modified": 1701598549, "price_change_number": 0}, {"appid": 2695830, "name": "ZAKESTA-Z", "last_modified": 1710242332, "price_change_number": 22766324}, {"appid": 2695850, "name": "SPIRITUS 2", "last_modified": 1701332666, "price_change_number": 21444057}, {"appid": 2695870, "name": "You Got Crabs", "last_modified": 1703313467, "price_change_number": 21606724}, {"appid": 2695910, "name": "\u53cc\u751f\u5e7b\u60f3", "last_modified": 1703585391, "price_change_number": 22736671}, {"appid": 2695940, "name": "PANICORE", "last_modified": 1710165871, "price_change_number": 0}, {"appid": 2695960, "name": "Memories of Glass Maiden", "last_modified": 1709034095, "price_change_number": 22547254}, {"appid": 2695970, "name": "\u5c11\u5e74\u6c5f\u5c71", "last_modified": 1703649426, "price_change_number": 22736671}, {"appid": 2696050, "name": "\u30e4\u30ea\u30e2\u30ce", "last_modified": 1710400308, "price_change_number": 0}, {"appid": 2696060, "name": "Elf Discipline Ceremony", "last_modified": 1710482192, "price_change_number": 22690841}, {"appid": 2696070, "name": "Solo leeching~35-Year-Old Magician Journey", "last_modified": 1710484241, "price_change_number": 0}, {"appid": 2696080, "name": "Dream of the Star Haven", "last_modified": 1707713509, "price_change_number": 22736671}, {"appid": 2696100, "name": "Scary Psycho Lady Simulator", "last_modified": 1709164985, "price_change_number": 22699586}, {"appid": 2696120, "name": "Shadow Album", "last_modified": 1710072875, "price_change_number": 0}, {"appid": 2696140, "name": "Nothing DOG", "last_modified": 1704544464, "price_change_number": 0}, {"appid": 2696160, "name": "Robot Tank Battle", "last_modified": 1709827052, "price_change_number": 0}, {"appid": 2696170, "name": "Jooin's Romance Fantasy", "last_modified": 1707829253, "price_change_number": 22736671}, {"appid": 2696200, "name": "Futanari College - Episode 1 [18+] \ud83c\udf53 \ud83e\udd13", "last_modified": 1703134945, "price_change_number": 22766324}, {"appid": 2696310, "name": "Last Castle Guardians", "last_modified": 1706182501, "price_change_number": 22766324}, {"appid": 2696320, "name": "Thought Experiment Simulator", "last_modified": 1709961246, "price_change_number": 0}, {"appid": 2696360, "name": "\u8ff7\u5931\uff1a\u5f02\u57df", "last_modified": 1706534673, "price_change_number": 22766324}, {"appid": 2696390, "name": "Guns And Draguns", "last_modified": 1710279751, "price_change_number": 0}, {"appid": 2696400, "name": "Magical Mic Duel: Senpai, Hear My Spell", "last_modified": 1709516046, "price_change_number": 0}, {"appid": 2696420, "name": "Chronocide", "last_modified": 1709105397, "price_change_number": 0}, {"appid": 2696430, "name": "Game Tester Quest", "last_modified": 1710481725, "price_change_number": 22104305}, {"appid": 2696480, "name": "Nothing", "last_modified": 1704906722, "price_change_number": 22736671}, {"appid": 2696520, "name": "Something", "last_modified": 1705085497, "price_change_number": 22766324}, {"appid": 2696530, "name": "Idle Percent", "last_modified": 1701446461, "price_change_number": 22766324}, {"appid": 2696550, "name": "Aquametsis", "last_modified": 1709132983, "price_change_number": 0}, {"appid": 2696570, "name": "Storm's Eye", "last_modified": 1709546519, "price_change_number": 0}, {"appid": 2696590, "name": "Case Guardians", "last_modified": 1702892246, "price_change_number": 0}, {"appid": 2696660, "name": "Kiopioke!", "last_modified": 1709069559, "price_change_number": 0}, {"appid": 2696680, "name": "BABAVA's Playspace", "last_modified": 1705000636, "price_change_number": 0}, {"appid": 2696750, "name": "Thin Way", "last_modified": 1704532206, "price_change_number": 0}, {"appid": 2696760, "name": "Starlight Legacy", "last_modified": 1708900962, "price_change_number": 0}, {"appid": 2696770, "name": "Purrs in Heaven", "last_modified": 1707331382, "price_change_number": 22766324}, {"appid": 2696780, "name": "Space Accident VR", "last_modified": 1710361589, "price_change_number": 0}, {"appid": 2696850, "name": "Xeno Runners", "last_modified": 1709751877, "price_change_number": 22626181}, {"appid": 2696970, "name": "Monologue: Winter melancholy", "last_modified": 1707256210, "price_change_number": 22766324}, {"appid": 2697010, "name": "SoLo", "last_modified": 1700687336, "price_change_number": 0}, {"appid": 2697030, "name": "I STILL LIVE UNDER YOUR HOUSE", "last_modified": 1707593929, "price_change_number": 0}, {"appid": 2697060, "name": "Cumdy", "last_modified": 1703781776, "price_change_number": 22736671}, {"appid": 2697070, "name": "Circus of TimTim - Mascot Horror Game", "last_modified": 1709673190, "price_change_number": 0}, {"appid": 2697090, "name": "Airborne Arena", "last_modified": 1706207654, "price_change_number": 0}, {"appid": 2697180, "name": "Ink of Fate", "last_modified": 1704742067, "price_change_number": 0}, {"appid": 2697200, "name": "Lunar's Chosen - Episode 2", "last_modified": 1708559463, "price_change_number": 0}, {"appid": 2697210, "name": "Detective Bass 2: The Case of the Stolen Pearls", "last_modified": 1702733274, "price_change_number": 0}, {"appid": 2697250, "name": "Gran Carismo", "last_modified": 1709485927, "price_change_number": 22513195}, {"appid": 2697360, "name": "Planecraft", "last_modified": 1703501604, "price_change_number": 22111421}, {"appid": 2697370, "name": "Spirita Battler", "last_modified": 1702482139, "price_change_number": 0}, {"appid": 2697380, "name": "Arsenal", "last_modified": 1703750466, "price_change_number": 22087090}]