[{"appid": 1392170, "name": "Schastye", "last_modified": 1614012394, "price_change_number": 22766324}, {"appid": 1392190, "name": "Rock Paper Sock", "last_modified": 1639497786, "price_change_number": 22766324}, {"appid": 1392230, "name": "Road Home", "last_modified": 1612346975, "price_change_number": 22766324}, {"appid": 1392240, "name": "Floathink", "last_modified": 1605277913, "price_change_number": 22767857}, {"appid": 1392280, "name": "Cyber Drive", "last_modified": 1667020969, "price_change_number": 21760363}, {"appid": 1392340, "name": "Shop Tycoon: Prepare your wallet", "last_modified": 1710147548, "price_change_number": 22766324}, {"appid": 1392390, "name": "REINCARNATION ASURA ZALANDARA Journey of carnage and redemption", "last_modified": 1662215142, "price_change_number": 22766324}, {"appid": 1392410, "name": "Seeking Revenge", "last_modified": 1608803335, "price_change_number": 22766324}, {"appid": 1392430, "name": "\u308f\u3093\u3053\u306e\u6069\u8fd4\u3057", "last_modified": 1705111631, "price_change_number": 22766324}, {"appid": 1392450, "name": "Deadlane", "last_modified": 1672845659, "price_change_number": 0}, {"appid": 1392460, "name": "\u8a85\u795e\u8a08\u756b", "last_modified": 1598437119, "price_change_number": 11351614}, {"appid": 1392480, "name": "Protocol Endfall", "last_modified": 1653821340, "price_change_number": 0}, {"appid": 1392490, "name": "Forklift Load", "last_modified": 1667373866, "price_change_number": 22766324}, {"appid": 1392510, "name": "The logic inside", "last_modified": 1598590234, "price_change_number": 22345113}, {"appid": 1392520, "name": "Life of trophy", "last_modified": 1617004519, "price_change_number": 11148671}, {"appid": 1392540, "name": "\u7f04\u9ed8\u661f\u7a7a Silent Space", "last_modified": 1604654365, "price_change_number": 21760363}, {"appid": 1392560, "name": "Serious Fun Football", "last_modified": 1710278955, "price_change_number": 22766324}, {"appid": 1392570, "name": "Dream Knights", "last_modified": 1598977386, "price_change_number": 12429103}, {"appid": 1392590, "name": "VIETNAM WAR PLATOON \u8d8a\u6218\u6392 (AI WAR Game)", "last_modified": 1600702289, "price_change_number": 11351614}, {"appid": 1392600, "name": "Kazakh Drive", "last_modified": 1603029950, "price_change_number": 21760363}, {"appid": 1392650, "name": "BLASTRONAUT", "last_modified": 1691359115, "price_change_number": 22766324}, {"appid": 1392660, "name": "Ice star Chapter 2", "last_modified": 1669740195, "price_change_number": 19055067}, {"appid": 1392670, "name": "Unbeliever", "last_modified": 1598300093, "price_change_number": 22736671}, {"appid": 1392690, "name": "Gravitational", "last_modified": 1688595498, "price_change_number": 22766324}, {"appid": 1392700, "name": "AGOS - A Game Of Space", "last_modified": 1679594848, "price_change_number": 22766324}, {"appid": 1392750, "name": "Lost Patrol", "last_modified": 1599047483, "price_change_number": 22766324}, {"appid": 1392760, "name": "Furry Heroes", "last_modified": 1634917927, "price_change_number": 22766324}, {"appid": 1392770, "name": "Practical Shooting Simulator", "last_modified": 1626972997, "price_change_number": 19141257}, {"appid": 1392780, "name": "The Companion", "last_modified": 1652269966, "price_change_number": 22766324}, {"appid": 1392790, "name": "Asteroids... But Roguelite", "last_modified": 1608593959, "price_change_number": 22766324}, {"appid": 1392820, "name": "Milk inside a bag of milk inside a bag of milk", "last_modified": 1689509158, "price_change_number": 22766324}, {"appid": 1392860, "name": "Little Nightmares III", "last_modified": 1695718230, "price_change_number": 0}, {"appid": 1392960, "name": "STORY OF SEASONS: Pioneers of Olive Town", "last_modified": 1705613551, "price_change_number": 22766324}, {"appid": 1392980, "name": "Leif's Adventure: Netherworld Hero", "last_modified": 1709886790, "price_change_number": 0}, {"appid": 1393080, "name": "Labyrinths of the World: Hearts of the Planet Collector's Edition", "last_modified": 1597686778, "price_change_number": 21760363}, {"appid": 1393100, "name": "Block Arena", "last_modified": 1604798530, "price_change_number": 22736671}, {"appid": 1393120, "name": "Get Out! Snakes!", "last_modified": 1622249630, "price_change_number": 22312985}, {"appid": 1393210, "name": "Dashie's Puh-ranormal Activity", "last_modified": 1695069802, "price_change_number": 20336035}, {"appid": 1393220, "name": "Electrify", "last_modified": 1614760541, "price_change_number": 9795476}, {"appid": 1393270, "name": "12 bananas", "last_modified": 1600281807, "price_change_number": 22736671}, {"appid": 1393310, "name": "Space Hole 2020", "last_modified": 1708557412, "price_change_number": 22766324}, {"appid": 1393320, "name": "Keyword: A Spider's Thread", "last_modified": 1666664549, "price_change_number": 22766324}, {"appid": 1393340, "name": "Battle Hunters", "last_modified": 1605410677, "price_change_number": 10743266}, {"appid": 1393350, "name": "Swaying Girl", "last_modified": 1687331389, "price_change_number": 22766324}, {"appid": 1393360, "name": "Onder", "last_modified": 1601517324, "price_change_number": 15351989}, {"appid": 1393370, "name": "Actraiser Renaissance", "last_modified": 1684722988, "price_change_number": 22766324}, {"appid": 1393380, "name": "Reverse Defenders", "last_modified": 1650675496, "price_change_number": 22766324}, {"appid": 1393410, "name": "Seek Girl V", "last_modified": 1708955731, "price_change_number": 22766324}, {"appid": 1393420, "name": "TOKOYO: The Tower of Perpetuity", "last_modified": 1703141439, "price_change_number": 22766324}, {"appid": 1393430, "name": "Banality Wars Carridin", "last_modified": 1660329506, "price_change_number": 0}, {"appid": 1393440, "name": "Hillside", "last_modified": 1602720330, "price_change_number": 0}, {"appid": 1393460, "name": "Mythicard", "last_modified": 1667728036, "price_change_number": 22736671}, {"appid": 1393480, "name": "Union", "last_modified": 1601533212, "price_change_number": 21776138}, {"appid": 1393490, "name": "CheeseCube", "last_modified": 1695722599, "price_change_number": 22766324}, {"appid": 1393500, "name": "Time Break Chronicles", "last_modified": 1710444125, "price_change_number": 22766324}, {"appid": 1393550, "name": "\u30b5\u30d6\u30ea\u30df\u30ca\u30eb\u30ec\u30b8\u30aa\u30f3", "last_modified": 1674996883, "price_change_number": 21201610}, {"appid": 1393560, "name": "Self gunsbase 2D History Shooter", "last_modified": 1694681537, "price_change_number": 19922988}, {"appid": 1393570, "name": "Superbugs: Awaken", "last_modified": 1648885106, "price_change_number": 22766324}, {"appid": 1393580, "name": "The Amulet of AmunRun", "last_modified": 1651079130, "price_change_number": 21760363}, {"appid": 1393610, "name": "CLASSIC TANKS 2020", "last_modified": 1599510129, "price_change_number": 22766324}, {"appid": 1393620, "name": "Sand Witch Adventures", "last_modified": 1626549598, "price_change_number": 0}, {"appid": 1393630, "name": "XGAMEX", "last_modified": 1698129767, "price_change_number": 0}, {"appid": 1393640, "name": "Home Designer - Living Room", "last_modified": 1667148680, "price_change_number": 22766324}, {"appid": 1393650, "name": "BlockBustersVR", "last_modified": 1605619185, "price_change_number": 21451968}, {"appid": 1393670, "name": "Los Cops", "last_modified": 1680076695, "price_change_number": 0}, {"appid": 1393680, "name": "Supreme Fighters", "last_modified": 1707867335, "price_change_number": 22736671}, {"appid": 1393690, "name": "WAVER: A Typing Adventure", "last_modified": 1629478822, "price_change_number": 18186143}, {"appid": 1393740, "name": "Vincula", "last_modified": 1652746071, "price_change_number": 22736671}, {"appid": 1393750, "name": "Ocean's Heart", "last_modified": 1688039663, "price_change_number": 22776099}, {"appid": 1393770, "name": "Fury Knight", "last_modified": 1708025270, "price_change_number": 22766324}, {"appid": 1393800, "name": "Loofy", "last_modified": 1604227100, "price_change_number": 22312985}, {"appid": 1393810, "name": "Surabaya Inferno", "last_modified": 1687960186, "price_change_number": 22766324}, {"appid": 1393820, "name": "Prodigal", "last_modified": 1709051613, "price_change_number": 22766324}, {"appid": 1393830, "name": "INFLUXIS", "last_modified": 1705851934, "price_change_number": 22736671}, {"appid": 1393850, "name": "Outer Frontier", "last_modified": 1617376319, "price_change_number": 22462125}, {"appid": 1393910, "name": "Jolly Good: Cakes and Ale", "last_modified": 1683815924, "price_change_number": 22766324}, {"appid": 1393950, "name": "REM Cycles", "last_modified": 1617206661, "price_change_number": 13581874}, {"appid": 1393960, "name": "Battle Command", "last_modified": 1598947589, "price_change_number": 22766324}, {"appid": 1393970, "name": "My Jigsaw Adventures - The Source of Power", "last_modified": 1667384166, "price_change_number": 22766324}, {"appid": 1394030, "name": "CESSPOOL", "last_modified": 1695987332, "price_change_number": 20514970}, {"appid": 1394040, "name": "Flixy Cats", "last_modified": 1618543979, "price_change_number": 11243413}, {"appid": 1394060, "name": "Viking Idle", "last_modified": 1599237148, "price_change_number": 18186143}, {"appid": 1394070, "name": "Brock Crocodile", "last_modified": 1662761606, "price_change_number": 0}, {"appid": 1394090, "name": "Power of Ten - Demo", "last_modified": 1602455064, "price_change_number": 22736671}, {"appid": 1394100, "name": "S.H.E.L.T.E.R. - An Apocalyptic Tale", "last_modified": 1670980051, "price_change_number": 22766324}, {"appid": 1394130, "name": "Breach Wanderers", "last_modified": 1687528825, "price_change_number": 22213363}, {"appid": 1394140, "name": "You Can Pet The Dog VR", "last_modified": 1623248067, "price_change_number": 19515800}, {"appid": 1394150, "name": "Official Wicked Vixen Silicone Scramble", "last_modified": 1600304693, "price_change_number": 15820056}, {"appid": 1394210, "name": "Strike VR", "last_modified": 1599830696, "price_change_number": 18019561}, {"appid": 1394240, "name": "VirtuaCreature", "last_modified": 1703180057, "price_change_number": 21760363}, {"appid": 1394250, "name": "Ryewood Town", "last_modified": 1670350467, "price_change_number": 0}, {"appid": 1394270, "name": "SCP: Escape Together", "last_modified": 1638071021, "price_change_number": 22736671}, {"appid": 1394320, "name": "Magic Trick", "last_modified": 1621041139, "price_change_number": 22766324}, {"appid": 1394330, "name": "\u4e71\u4e16\u5947\u8c0bStratagem in troubled times", "last_modified": 1606163371, "price_change_number": 13301447}, {"appid": 1394340, "name": "DreamDasher", "last_modified": 1605388001, "price_change_number": 22736671}, {"appid": 1394370, "name": "Super Symbol Boys", "last_modified": 1707177666, "price_change_number": 22736671}, {"appid": 1394400, "name": "Gump", "last_modified": 1698264333, "price_change_number": 22736671}, {"appid": 1394410, "name": "Mysterica", "last_modified": 1618922715, "price_change_number": 22736671}, {"appid": 1394420, "name": "Dallen Clicker Ultimate", "last_modified": 1682744437, "price_change_number": 22766324}, {"appid": 1394440, "name": "GAME OVER", "last_modified": 1635907169, "price_change_number": 0}, {"appid": 1394460, "name": "RXC - Rally Cross Challenge", "last_modified": 1672170803, "price_change_number": 18186143}, {"appid": 1394470, "name": "Umami Grove", "last_modified": 1701982296, "price_change_number": 0}, {"appid": 1394480, "name": "Rocco's Island: Ring to End the Pain", "last_modified": 1699531782, "price_change_number": 22766324}, {"appid": 1394490, "name": "Galactic Trooper Armada", "last_modified": 1598530774, "price_change_number": 22766324}, {"appid": 1394500, "name": "Frontline: World War II", "last_modified": 1709458448, "price_change_number": 22766324}, {"appid": 1394510, "name": "Emurinoo", "last_modified": 1601351711, "price_change_number": 15456496}, {"appid": 1394520, "name": "Path to Prosperity", "last_modified": 1625166973, "price_change_number": 11351614}, {"appid": 1394540, "name": "Niko and the Cubic Curse", "last_modified": 1705040135, "price_change_number": 15351741}, {"appid": 1394550, "name": "Tales From The Under-Realm: Hazel", "last_modified": 1684501900, "price_change_number": 21760363}, {"appid": 1394570, "name": "Pass to Hell", "last_modified": 1599094640, "price_change_number": 19813381}, {"appid": 1394580, "name": "\u9e7f\u6613\u60f3\u8981\u6d3b\u5230\u4e16\u754c\u5c3d\u5934", "last_modified": 1599719171, "price_change_number": 11391213}, {"appid": 1394600, "name": "Invasion Resistance 2", "last_modified": 1598803941, "price_change_number": 11351614}, {"appid": 1394640, "name": "Dark Room VR", "last_modified": 1598988697, "price_change_number": 22736671}, {"appid": 1394650, "name": "Detained: Too Good for School", "last_modified": 1710271098, "price_change_number": 0}, {"appid": 1394660, "name": "Isometric World: Frame of Mind", "last_modified": 1698628569, "price_change_number": 0}, {"appid": 1394680, "name": "Soul Catcher", "last_modified": 1667470841, "price_change_number": 22784193}, {"appid": 1394700, "name": "Takorita Meets Fries", "last_modified": 1709899359, "price_change_number": 22766324}, {"appid": 1394720, "name": "Block Dungeon", "last_modified": 1626415613, "price_change_number": 22766324}, {"appid": 1394750, "name": "Mahjong World Contest 2", "last_modified": 1687353472, "price_change_number": 21726663}, {"appid": 1394760, "name": "Mahjong Carnaval", "last_modified": 1687353864, "price_change_number": 22513184}, {"appid": 1394800, "name": "Rebirth:Mr Wang", "last_modified": 1671867284, "price_change_number": 22766324}, {"appid": 1394810, "name": "Colossus Down", "last_modified": 1701438300, "price_change_number": 22766324}, {"appid": 1394830, "name": "LOCIS", "last_modified": 1641152852, "price_change_number": 22766324}, {"appid": 1394880, "name": "Wild Baffo", "last_modified": 1667216737, "price_change_number": 22766324}, {"appid": 1394930, "name": "MAMIYA", "last_modified": 1701510927, "price_change_number": 22766324}, {"appid": 1394940, "name": "Nak Sim: Fallen Warriors", "last_modified": 1708309968, "price_change_number": 21231629}, {"appid": 1394960, "name": "Winter Survival", "last_modified": 1710505004, "price_change_number": 22659348}, {"appid": 1394990, "name": "Heart of Summer", "last_modified": 1677439891, "price_change_number": 0}, {"appid": 1395000, "name": "Egypt Picross Pharaohs Riddles", "last_modified": 1687353912, "price_change_number": 21673089}, {"appid": 1395010, "name": "Magic Griddlers", "last_modified": 1687353955, "price_change_number": 21312825}, {"appid": 1395020, "name": "Picross Beach Paradise", "last_modified": 1687353998, "price_change_number": 22766324}, {"appid": 1395030, "name": "Kathy Rain: Director's Cut", "last_modified": 1709552837, "price_change_number": 22766324}, {"appid": 1395040, "name": "CyberThreat", "last_modified": 1663764947, "price_change_number": 0}, {"appid": 1395080, "name": "The Disaster", "last_modified": 1627745638, "price_change_number": 13581874}, {"appid": 1395120, "name": "At Eve\u2019s Wake Definitive Edition", "last_modified": 1686773022, "price_change_number": 22766324}, {"appid": 1395170, "name": "Stones of the Revenant", "last_modified": 1599652686, "price_change_number": 19515800}, {"appid": 1395180, "name": "Raid!", "last_modified": 1601260086, "price_change_number": 22736671}, {"appid": 1395190, "name": "BLASK 2", "last_modified": 1611854284, "price_change_number": 22766324}, {"appid": 1395230, "name": "Almost My Floor: Prologue", "last_modified": 1673813545, "price_change_number": 22736671}, {"appid": 1395250, "name": "Cube Crisis", "last_modified": 1604332391, "price_change_number": 9906175}, {"appid": 1395270, "name": "Haiki", "last_modified": 1683293632, "price_change_number": 22766324}, {"appid": 1395310, "name": "World of Soccer RELOADED", "last_modified": 1613845254, "price_change_number": 22736671}, {"appid": 1395330, "name": "Venture Valley", "last_modified": 1687819837, "price_change_number": 22736671}, {"appid": 1395380, "name": "Evolutis: Duality", "last_modified": 1691621702, "price_change_number": 0}, {"appid": 1395400, "name": "The Corruption Within", "last_modified": 1625509874, "price_change_number": 22766324}, {"appid": 1395410, "name": "Jetscout: Mystery of the Valunians", "last_modified": 1667161522, "price_change_number": 21760363}, {"appid": 1395420, "name": "Human Diaspora", "last_modified": 1688988947, "price_change_number": 22736671}, {"appid": 1395450, "name": "Shell Shuffle", "last_modified": 1619887609, "price_change_number": 22766324}, {"appid": 1395470, "name": "Glory", "last_modified": 1599057976, "price_change_number": 11351614}, {"appid": 1395480, "name": "A Midnight Village Story", "last_modified": 1672941060, "price_change_number": 17308989}, {"appid": 1395510, "name": "Solar Scion", "last_modified": 1667408432, "price_change_number": 15351989}, {"appid": 1395520, "name": "Eldritch House", "last_modified": 1706789700, "price_change_number": 0}, {"appid": 1395540, "name": "BOT.vinnik Chess: Winning Patterns", "last_modified": 1683143460, "price_change_number": 22312985}, {"appid": 1395560, "name": "Kandidatos", "last_modified": 1690916829, "price_change_number": 22766324}, {"appid": 1395600, "name": "Party Parkade", "last_modified": 1650981385, "price_change_number": 22736671}, {"appid": 1395630, "name": "Cute dragon Yongyong", "last_modified": 1612195159, "price_change_number": 22736671}, {"appid": 1395660, "name": "Sphere Invasion", "last_modified": 1606064993, "price_change_number": 10401154}, {"appid": 1395710, "name": "Daisy Flies to the Moon", "last_modified": 1708731676, "price_change_number": 22766324}, {"appid": 1395750, "name": "Dasher", "last_modified": 1657831445, "price_change_number": 15632967}, {"appid": 1395760, "name": "Reshaping Mars", "last_modified": 1680971569, "price_change_number": 22766324}, {"appid": 1395780, "name": "Punchout: Music", "last_modified": 1601263448, "price_change_number": 13853601}, {"appid": 1395830, "name": "Hoplegs", "last_modified": 1663069044, "price_change_number": 22766324}, {"appid": 1395850, "name": "Home & Dungeon", "last_modified": 1709111165, "price_change_number": 22766324}, {"appid": 1395890, "name": "Super Dango", "last_modified": 1615605784, "price_change_number": 10772097}, {"appid": 1395900, "name": "Bouncer Story", "last_modified": 1604418791, "price_change_number": 22766324}, {"appid": 1395920, "name": "GrappleWell", "last_modified": 1658379173, "price_change_number": 21760363}, {"appid": 1396010, "name": "Asian Riddles 2", "last_modified": 1687354064, "price_change_number": 22104294}, {"appid": 1396020, "name": "Fill and Cross Royal Riddles", "last_modified": 1687354123, "price_change_number": 22104294}, {"appid": 1396050, "name": "Kirakira stars idol project Reika", "last_modified": 1606360027, "price_change_number": 22766324}, {"appid": 1396140, "name": "Hexagroove: Tactical DJ", "last_modified": 1694149114, "price_change_number": 22766324}, {"appid": 1396150, "name": "\u7d20\u6575\u306a\u5f7c\u5973\u306e\u4f5c\u308a\u65b9", "last_modified": 1637777906, "price_change_number": 22766324}, {"appid": 1396160, "name": "SaltyFishGo", "last_modified": 1599564911, "price_change_number": 0}, {"appid": 1396170, "name": "Paint Royale", "last_modified": 1692986490, "price_change_number": 22736671}, {"appid": 1396190, "name": "DE-EXIT - Eternal Matters", "last_modified": 1707747228, "price_change_number": 22766324}, {"appid": 1396240, "name": "Contraband Police: Prologue", "last_modified": 1701335711, "price_change_number": 22736671}, {"appid": 1396260, "name": "FALAFEL Restaurant Simulator", "last_modified": 1708547331, "price_change_number": 22766324}, {"appid": 1396290, "name": "Chess Mega Bundle", "last_modified": 1623086502, "price_change_number": 11752942}, {"appid": 1396310, "name": "Orcs and Outlaws", "last_modified": 1701636279, "price_change_number": 0}, {"appid": 1396350, "name": "Anamnesis", "last_modified": 1617380677, "price_change_number": 21201610}, {"appid": 1396380, "name": "ANIME WORLD", "last_modified": 1697873096, "price_change_number": 22766324}, {"appid": 1396390, "name": "Jump Hero: Beginning", "last_modified": 1628315503, "price_change_number": 22766324}, {"appid": 1396450, "name": "\u6700\u672b\u884c\u7a0b\uff1a\u80dc\u5229\u8def19\u53f7", "last_modified": 1661251372, "price_change_number": 22766324}, {"appid": 1396480, "name": "MonsterSoft", "last_modified": 1630174964, "price_change_number": 22766324}, {"appid": 1396490, "name": "All For Nought - Tic Tac Toe", "last_modified": 1599137270, "price_change_number": 22736671}, {"appid": 1396500, "name": "Thyra Adventure", "last_modified": 1608747719, "price_change_number": 11974414}, {"appid": 1396540, "name": "Twilight Wars", "last_modified": 1708468133, "price_change_number": 0}, {"appid": 1396580, "name": "Hey ma i'm a Dragon Now", "last_modified": 1668471981, "price_change_number": 22766324}, {"appid": 1396610, "name": "Do It With Hay", "last_modified": 1599233235, "price_change_number": 22766324}, {"appid": 1396630, "name": "Hollow Mind: The Lost Puppy", "last_modified": 1631820626, "price_change_number": 22736671}, {"appid": 1396870, "name": "ENCHAIN", "last_modified": 1704964590, "price_change_number": 0}, {"appid": 1396890, "name": "Boss of this gym", "last_modified": 1655415126, "price_change_number": 19515800}, {"appid": 1396950, "name": "The mouse and the cheese", "last_modified": 1632508821, "price_change_number": 21902150}, {"appid": 1396970, "name": "Chess on Ice", "last_modified": 1600356986, "price_change_number": 0}, {"appid": 1396980, "name": "The Sealed Ampoule", "last_modified": 1646098805, "price_change_number": 22766324}, {"appid": 1397000, "name": "Zodiac DX", "last_modified": 1668931139, "price_change_number": 22766324}, {"appid": 1397010, "name": "1980", "last_modified": 1598858585, "price_change_number": 22736671}, {"appid": 1397030, "name": "Survive or Thrive", "last_modified": 1677261053, "price_change_number": 22766324}, {"appid": 1397040, "name": "Sanguine Melancholia", "last_modified": 1599132984, "price_change_number": 22736671}, {"appid": 1397050, "name": "Square vs Triangles", "last_modified": 1603528851, "price_change_number": 21201610}, {"appid": 1397060, "name": "Little Brother's Turn", "last_modified": 1609693759, "price_change_number": 10387423}, {"appid": 1397070, "name": "Back to the Scene", "last_modified": 1708886781, "price_change_number": 22766324}, {"appid": 1397110, "name": "Harthorn", "last_modified": 1679147845, "price_change_number": 22766324}, {"appid": 1397130, "name": "Primateria", "last_modified": 1705293991, "price_change_number": 22766324}, {"appid": 1397140, "name": "The Last Show of Mr. Chardish: Act I", "last_modified": 1692610974, "price_change_number": 22736671}, {"appid": 1397160, "name": "Pulut Adventure RPG", "last_modified": 1600156793, "price_change_number": 18040534}, {"appid": 1397170, "name": "Anime Wave Simulator", "last_modified": 1708932142, "price_change_number": 22766324}, {"appid": 1397180, "name": "Three Dimension", "last_modified": 1640329285, "price_change_number": 14036087}, {"appid": 1397230, "name": "VR Time Machine Travelling in history: Visit ancient Egypt, Babylon and Greece in B.C. 400", "last_modified": 1659581002, "price_change_number": 22766324}, {"appid": 1397240, "name": "MEGAJUMP", "last_modified": 1675286328, "price_change_number": 22736671}, {"appid": 1397280, "name": "Slime Pandemic TD", "last_modified": 1630177482, "price_change_number": 21760363}, {"appid": 1397290, "name": "Comet 64", "last_modified": 1669125454, "price_change_number": 22766324}, {"appid": 1397300, "name": "Kyma", "last_modified": 1682422688, "price_change_number": 18152897}, {"appid": 1397350, "name": "\u597d\u4e45\u4e0d\u89c1 - Long Time No See", "last_modified": 1601541130, "price_change_number": 11351614}, {"appid": 1397360, "name": "Shattered Runes", "last_modified": 1613242410, "price_change_number": 11390213}, {"appid": 1397390, "name": "The Break-In", "last_modified": 1689627306, "price_change_number": 22766324}, {"appid": 1397410, "name": "\u70c8\u7130\u5929\u4e0b", "last_modified": 1598172441, "price_change_number": 0}, {"appid": 1397470, "name": "Tsuro - The Game of The Path", "last_modified": 1603174053, "price_change_number": 22766324}, {"appid": 1397500, "name": "Combat League", "last_modified": 1636573917, "price_change_number": 0}, {"appid": 1397530, "name": "Monochro", "last_modified": 1602427442, "price_change_number": 22766324}, {"appid": 1397540, "name": "On Pixels: A lights out game", "last_modified": 1605556634, "price_change_number": 21760363}, {"appid": 1397580, "name": "Eidols", "last_modified": 1655492271, "price_change_number": 0}, {"appid": 1397620, "name": "Flat Earth Simulator", "last_modified": 1607637436, "price_change_number": 22766324}, {"appid": 1397650, "name": "Jetborne Racing", "last_modified": 1625066280, "price_change_number": 22766324}, {"appid": 1397680, "name": "Glory Hold", "last_modified": 1598055640, "price_change_number": 0}, {"appid": 1397690, "name": "Riot At World", "last_modified": 1599483465, "price_change_number": 11351614}, {"appid": 1397710, "name": "Operation TP", "last_modified": 1663867121, "price_change_number": 22736671}, {"appid": 1397720, "name": "Red Sector", "last_modified": 1687141715, "price_change_number": 17882327}, {"appid": 1397760, "name": "Pulse Jumper", "last_modified": 1640361283, "price_change_number": 22736671}, {"appid": 1397790, "name": "Samurai Gunn 2", "last_modified": 1680534281, "price_change_number": 22411605}, {"appid": 1397800, "name": "Please Wake Up", "last_modified": 1611908748, "price_change_number": 21312825}, {"appid": 1397810, "name": "Ducktopia", "last_modified": 1628687939, "price_change_number": 22766324}, {"appid": 1397820, "name": "Sky Mirror \u00b7 Strolling", "last_modified": 1625155913, "price_change_number": 22736671}, {"appid": 1397830, "name": "Presidential Running Games", "last_modified": 1642808310, "price_change_number": 22736671}, {"appid": 1397840, "name": "Cult of Dawn", "last_modified": 1708026026, "price_change_number": 0}, {"appid": 1397850, "name": "Circle Tank", "last_modified": 1599486383, "price_change_number": 22736671}, {"appid": 1397880, "name": "The Weald", "last_modified": 1619649276, "price_change_number": 0}, {"appid": 1397920, "name": "Mr.Mine", "last_modified": 1710351789, "price_change_number": 22736671}, {"appid": 1397940, "name": "Prototype Zordi Mi l\u00e9", "last_modified": 1663393347, "price_change_number": 22736671}, {"appid": 1397950, "name": "The Scarlet Capital \u7eef\u7ea2\u4e4b\u90fd", "last_modified": 1603162399, "price_change_number": 0}, {"appid": 1397960, "name": "One Night on Halloween", "last_modified": 1604743061, "price_change_number": 22766324}, {"appid": 1397980, "name": "THE NORMAL THING", "last_modified": 1607666505, "price_change_number": 22736671}, {"appid": 1398070, "name": "The Book of Bondmaids", "last_modified": 1698398763, "price_change_number": 22766324}, {"appid": 1398080, "name": "Seaside Cafe Story", "last_modified": 1604545488, "price_change_number": 22766324}, {"appid": 1398100, "name": "Orwell's Animal Farm", "last_modified": 1613035991, "price_change_number": 22766324}, {"appid": 1398110, "name": "Space Pirate King", "last_modified": 1678445376, "price_change_number": 21312825}, {"appid": 1398120, "name": "The Hardest Thing Ever", "last_modified": 1667142922, "price_change_number": 18186143}, {"appid": 1398130, "name": "Head Bumper: Editcraft", "last_modified": 1661217109, "price_change_number": 15351989}, {"appid": 1398170, "name": "Mourning Inc.", "last_modified": 1638610276, "price_change_number": 22736671}, {"appid": 1398180, "name": "Porcini", "last_modified": 1708006364, "price_change_number": 22766324}, {"appid": 1398200, "name": "ADA: Al\u00e9m d' Aventura", "last_modified": 1668084008, "price_change_number": 0}, {"appid": 1398210, "name": "Selene ~Apoptosis~", "last_modified": 1686850250, "price_change_number": 22736671}, {"appid": 1398220, "name": "IMPAVIDVM", "last_modified": 1683591583, "price_change_number": 18655234}, {"appid": 1398270, "name": "Furgal's Jetpack", "last_modified": 1708025849, "price_change_number": 22766324}, {"appid": 1398280, "name": "Great Lakes Simulator", "last_modified": 1695725523, "price_change_number": 22766324}, {"appid": 1398290, "name": "Cr\u00f4nicas de Landulph", "last_modified": 1667903793, "price_change_number": 19703871}, {"appid": 1398300, "name": "Suspicious Shuffle", "last_modified": 1694739399, "price_change_number": 22002814}, {"appid": 1398340, "name": "Paintball with Friends", "last_modified": 1665180477, "price_change_number": 0}, {"appid": 1398390, "name": "SPACE / MECH / PILOT", "last_modified": 1664942558, "price_change_number": 22773139}, {"appid": 1398400, "name": "Florida Man: Hurricane Hijinks", "last_modified": 1681665642, "price_change_number": 13581874}, {"appid": 1398410, "name": "Reginald's Death Arena", "last_modified": 1624554172, "price_change_number": 22736671}, {"appid": 1398420, "name": "One Last Dungeon", "last_modified": 1608829972, "price_change_number": 13853601}, {"appid": 1398440, "name": "Transcender", "last_modified": 1601491370, "price_change_number": 22736671}, {"appid": 1398460, "name": "Line Leader", "last_modified": 1653598460, "price_change_number": 0}, {"appid": 1398470, "name": "Pop up Blaster", "last_modified": 1601080174, "price_change_number": 11351614}, {"appid": 1398500, "name": "MECHBLAZE", "last_modified": 1671073079, "price_change_number": 22766324}, {"appid": 1398510, "name": "Galaxy in Peril: Time Trouble", "last_modified": 1601521261, "price_change_number": 19515800}, {"appid": 1398570, "name": "Last Escape", "last_modified": 1697992428, "price_change_number": 22766324}, {"appid": 1398590, "name": "1001 Jigsaw World Tour Asia", "last_modified": 1687354243, "price_change_number": 21902150}, {"appid": 1398600, "name": "Fill and Cross World Contest", "last_modified": 1687354288, "price_change_number": 22312985}, {"appid": 1398630, "name": "\u65e0\u9650\u6b21\u5143", "last_modified": 1617037449, "price_change_number": 15351989}, {"appid": 1398660, "name": "CamGirls: Sophie X Rias", "last_modified": 1705065796, "price_change_number": 22766324}, {"appid": 1398670, "name": "Dating Life 2: Emily X Miley", "last_modified": 1705065861, "price_change_number": 22766324}, {"appid": 1398680, "name": "Negligee: Girls Night", "last_modified": 1705065908, "price_change_number": 22766324}, {"appid": 1398690, "name": "Negligee: Opposites Attract", "last_modified": 1705065999, "price_change_number": 22766324}, {"appid": 1398700, "name": "Animal Cafe", "last_modified": 1705066047, "price_change_number": 22766324}, {"appid": 1398710, "name": "Fairy Glade", "last_modified": 1705066077, "price_change_number": 22766324}, {"appid": 1398720, "name": "Water Girls", "last_modified": 1705066107, "price_change_number": 22766324}, {"appid": 1398730, "name": "Winter Wonderland", "last_modified": 1705066141, "price_change_number": 22766324}, {"appid": 1398740, "name": "The Chrono Jotter", "last_modified": 1702969364, "price_change_number": 22766324}, {"appid": 1398750, "name": "Sunset Mall", "last_modified": 1704923763, "price_change_number": 22513184}, {"appid": 1398790, "name": "Boobs VR", "last_modified": 1599292087, "price_change_number": 22766324}, {"appid": 1398820, "name": "Compost", "last_modified": 1602769838, "price_change_number": 13581874}, {"appid": 1398860, "name": "Rocket Squad", "last_modified": 1601391769, "price_change_number": 11351614}, {"appid": 1398890, "name": "Fast Jump", "last_modified": 1702964783, "price_change_number": 11351614}, {"appid": 1398900, "name": "Lost: Into Dolor", "last_modified": 1610845707, "price_change_number": 18186143}, {"appid": 1398910, "name": "Jorel\u2019s Brother and The Most Important Game of the Galaxy", "last_modified": 1706728035, "price_change_number": 22766324}, {"appid": 1398920, "name": "Virtuverse", "last_modified": 1639986909, "price_change_number": 22736671}, {"appid": 1398950, "name": "Savage Tower Defense", "last_modified": 1609723667, "price_change_number": 18393071}, {"appid": 1398990, "name": "ANCIENT SOULS: Starship Renata", "last_modified": 1618681481, "price_change_number": 22766324}, {"appid": 1399030, "name": "Wacky Wizarding Dungeon", "last_modified": 1648669498, "price_change_number": 14751331}, {"appid": 1399040, "name": "This Is Not Chess", "last_modified": 1667003224, "price_change_number": 22766324}, {"appid": 1399080, "name": "The DioField Chronicle", "last_modified": 1696940654, "price_change_number": 22766324}, {"appid": 1399090, "name": "Life Simulator", "last_modified": 1708885503, "price_change_number": 22766324}, {"appid": 1399140, "name": "Boxing Coach", "last_modified": 1602821031, "price_change_number": 9815030}, {"appid": 1399150, "name": "VR Time Machine Travelling in ancient civilizations: Mayan Kingdom, Inca Empire, Indians, and Aztecs before conquest A.D.1000", "last_modified": 1658807061, "price_change_number": 22766324}, {"appid": 1399160, "name": "\u5fa1\u5251\u98de\u884c\u5c04\u51fb\u8bad\u7ec3\u7a7a\u95f4", "last_modified": 1664176937, "price_change_number": 18186143}, {"appid": 1399170, "name": "Nimbus INFINITY", "last_modified": 1687779113, "price_change_number": 22766324}, {"appid": 1399180, "name": "Lone Wolf: World War 2", "last_modified": 1671107910, "price_change_number": 10796181}, {"appid": 1399190, "name": "Blood Oath: When The Sword Rises", "last_modified": 1646520548, "price_change_number": 0}, {"appid": 1399210, "name": "Lumiland", "last_modified": 1613083239, "price_change_number": 19515800}, {"appid": 1399220, "name": "Raw April Day", "last_modified": 1696497363, "price_change_number": 0}, {"appid": 1399230, "name": "Hoovernauts", "last_modified": 1599938868, "price_change_number": 11351614}, {"appid": 1399240, "name": "Yotsume God -Reunion-", "last_modified": 1704940524, "price_change_number": 22766324}, {"appid": 1399250, "name": "Red Cap Zombie Hunter", "last_modified": 1646391349, "price_change_number": 18186143}, {"appid": 1399270, "name": "The Arena Guy", "last_modified": 1606989108, "price_change_number": 22766324}, {"appid": 1399280, "name": "The Lost Cube", "last_modified": 1688478815, "price_change_number": 22766324}, {"appid": 1399300, "name": "SOK PRO", "last_modified": 1683118878, "price_change_number": 22766324}, {"appid": 1399370, "name": "Cute Honey 2", "last_modified": 1709265413, "price_change_number": 22766324}, {"appid": 1399380, "name": "NUI", "last_modified": 1603896637, "price_change_number": 22766324}, {"appid": 1399400, "name": "VR historical journey to the Buddhist civilizations: VR ancient India and Asia", "last_modified": 1659429955, "price_change_number": 22766324}, {"appid": 1399440, "name": "Pets VR", "last_modified": 1646765113, "price_change_number": 21760363}, {"appid": 1399460, "name": "Museum Of Extravagance", "last_modified": 1631429734, "price_change_number": 18186143}, {"appid": 1399480, "name": "California Games (C64/DOS/Atari/Lynx/NES/SMS/Genesis)", "last_modified": 1687253764, "price_change_number": 22766324}, {"appid": 1399530, "name": "Walden Horde", "last_modified": 1659435773, "price_change_number": 0}, {"appid": 1399540, "name": "A Forgetful Loop", "last_modified": 1627996322, "price_change_number": 21760363}, {"appid": 1399590, "name": "Strike Buster Prototype", "last_modified": 1675353266, "price_change_number": 22766324}, {"appid": 1399600, "name": "District 99", "last_modified": 1613156469, "price_change_number": 22766324}, {"appid": 1399620, "name": "The Caretaker", "last_modified": 1625140703, "price_change_number": 22626142}, {"appid": 1399630, "name": "Lactea Volleyball", "last_modified": 1667067957, "price_change_number": 21760363}, {"appid": 1399660, "name": "My Little Prince - a jigsaw puzzle tale", "last_modified": 1634912576, "price_change_number": 22766324}, {"appid": 1399670, "name": "Instant Farmer - Logic Puzzle", "last_modified": 1708907061, "price_change_number": 22717541}, {"appid": 1399690, "name": "Reverie Knights Tactics", "last_modified": 1706872113, "price_change_number": 22766324}, {"appid": 1399700, "name": "Kapital: Sparks of Revolution", "last_modified": 1706871600, "price_change_number": 22766324}, {"appid": 1399720, "name": "Antimatter Dimensions", "last_modified": 1671837279, "price_change_number": 22736671}, {"appid": 1399750, "name": "Beholgar", "last_modified": 1644016467, "price_change_number": 22766324}, {"appid": 1399760, "name": "Randomlands", "last_modified": 1600693358, "price_change_number": 21760363}, {"appid": 1399800, "name": "Silver Squad: Age of the Vortex", "last_modified": 1647880326, "price_change_number": 0}, {"appid": 1399840, "name": "Neptunia Virtual Stars", "last_modified": 1619130693, "price_change_number": 22766324}, {"appid": 1399850, "name": "Squares Rage", "last_modified": 1628738426, "price_change_number": 21760363}, {"appid": 1399870, "name": "Bedtime Horror Stories", "last_modified": 1668527978, "price_change_number": 0}, {"appid": 1399900, "name": "PolyBeyond", "last_modified": 1632914230, "price_change_number": 22736671}, {"appid": 1399910, "name": "Crisis Arcana", "last_modified": 1600422739, "price_change_number": 11351614}, {"appid": 1399930, "name": "Furry Shades of Gay", "last_modified": 1707062626, "price_change_number": 22766324}, {"appid": 1399940, "name": "BATSU!", "last_modified": 1666935496, "price_change_number": 0}, {"appid": 1399990, "name": "Don't Die! Douche!", "last_modified": 1607442312, "price_change_number": 13581874}, {"appid": 1400000, "name": "Mint Works", "last_modified": 1602283718, "price_change_number": 15877556}, {"appid": 1400030, "name": "Dragon Acres", "last_modified": 1694442653, "price_change_number": 0}, {"appid": 1400040, "name": "The Cubedex of Boxes and Lines", "last_modified": 1602265103, "price_change_number": 0}, {"appid": 1400060, "name": "What's the Matter?", "last_modified": 1647024348, "price_change_number": 21760363}, {"appid": 1400070, "name": "Don't Cheat On Me", "last_modified": 1615705282, "price_change_number": 21760363}, {"appid": 1400080, "name": "Pre-Strike", "last_modified": 1628714943, "price_change_number": 22736671}, {"appid": 1400100, "name": "The Old House", "last_modified": 1658667814, "price_change_number": 22766324}, {"appid": 1400110, "name": "Sightbringer", "last_modified": 1670245409, "price_change_number": 22736671}, {"appid": 1400140, "name": "Way in the stars", "last_modified": 1601571249, "price_change_number": 11974414}, {"appid": 1400150, "name": "Pandemic Bunny", "last_modified": 1599942682, "price_change_number": 11351614}, {"appid": 1400170, "name": "TinyCrack", "last_modified": 1600383208, "price_change_number": 11351614}, {"appid": 1400180, "name": "Monster Girl Breeder", "last_modified": 1684169497, "price_change_number": 22481697}, {"appid": 1400190, "name": "Human-Like", "last_modified": 1608607843, "price_change_number": 16535181}, {"appid": 1400200, "name": "Mystery Case Files: The Harbinger Collector's Edition", "last_modified": 1598032079, "price_change_number": 21760363}, {"appid": 1400210, "name": "Death Drives A Bus", "last_modified": 1667441088, "price_change_number": 22766324}, {"appid": 1400260, "name": "Legendary Journeys", "last_modified": 1699194888, "price_change_number": 21760363}, {"appid": 1400270, "name": "Fox face kills!", "last_modified": 1616346634, "price_change_number": 22766324}, {"appid": 1400290, "name": "[Chilla's Art] Hanako | \u82b1\u5b50\u3055\u3093", "last_modified": 1662351812, "price_change_number": 22766324}, {"appid": 1400320, "name": "\uadf8 \uc5b4\ub290 \uc5ec\ub984\ub0a0\uc758 \uc774\uc57c\uae30", "last_modified": 1654651017, "price_change_number": 22736671}, {"appid": 1400350, "name": "Rescue Rina", "last_modified": 1703905195, "price_change_number": 22766324}, {"appid": 1400360, "name": "LemWars", "last_modified": 1602727251, "price_change_number": 15351989}, {"appid": 1400390, "name": "The First Confrontation", "last_modified": 1600631465, "price_change_number": 22736671}, {"appid": 1400480, "name": "Lost Gems", "last_modified": 1599974671, "price_change_number": 15597129}, {"appid": 1400520, "name": "Nomads of Driftland", "last_modified": 1659632349, "price_change_number": 22736671}, {"appid": 1400560, "name": "Priest vs. Poltergeist", "last_modified": 1606376416, "price_change_number": 0}, {"appid": 1400610, "name": "One Drunken Knight", "last_modified": 1669319843, "price_change_number": 22766324}, {"appid": 1400620, "name": "Ballsy! World Cup 2020", "last_modified": 1667219827, "price_change_number": 22766324}, {"appid": 1400630, "name": "Afterthought", "last_modified": 1709033695, "price_change_number": 21760363}, {"appid": 1400650, "name": "\u4e07\u4eba\u5272\u8349\u5854\u9632", "last_modified": 1602915008, "price_change_number": 9795476}, {"appid": 1400660, "name": "Rise of Piracy", "last_modified": 1708129225, "price_change_number": 0}, {"appid": 1400680, "name": "Impossible Mission II", "last_modified": 1599809497, "price_change_number": 22766324}, {"appid": 1400700, "name": "Confessions", "last_modified": 1683092993, "price_change_number": 21760363}, {"appid": 1400710, "name": "Gowf", "last_modified": 1704408381, "price_change_number": 0}, {"appid": 1400740, "name": "Petrol Blood", "last_modified": 1659718087, "price_change_number": 0}, {"appid": 1400750, "name": "Cartridge Monsters: Rebirth", "last_modified": 1705941569, "price_change_number": 0}, {"appid": 1400760, "name": "My Universe - My Baby", "last_modified": 1609947436, "price_change_number": 22766324}, {"appid": 1400830, "name": "Billie Bust Up", "last_modified": 1693233876, "price_change_number": 0}, {"appid": 1400850, "name": "Aza", "last_modified": 1705212076, "price_change_number": 22766324}, {"appid": 1400870, "name": "When The Night Comes", "last_modified": 1680275413, "price_change_number": 22766324}, {"appid": 1400910, "name": "Soundodger 2", "last_modified": 1681393861, "price_change_number": 22766324}, {"appid": 1400920, "name": "Flood Fill", "last_modified": 1600661171, "price_change_number": 18186143}, {"appid": 1400930, "name": "Save the Date", "last_modified": 1601904083, "price_change_number": 22736671}, {"appid": 1400940, "name": "Revolution Diabolique", "last_modified": 1680670008, "price_change_number": 22766324}, {"appid": 1400980, "name": "My Neighborhood Arcade", "last_modified": 1647510097, "price_change_number": 22736671}, {"appid": 1401020, "name": "Where Is My Vodka?", "last_modified": 1699488896, "price_change_number": 0}, {"appid": 1401070, "name": "Quest for Runia", "last_modified": 1686832616, "price_change_number": 22766324}, {"appid": 1401110, "name": "Near Sol", "last_modified": 1695276383, "price_change_number": 21760363}, {"appid": 1401130, "name": "Jajazinho e as Delicias de Cristais", "last_modified": 1699012766, "price_change_number": 22328556}, {"appid": 1401150, "name": "Black Hole Simulator", "last_modified": 1644456221, "price_change_number": 22766324}, {"appid": 1401170, "name": "World War 2: Strategy Simulator", "last_modified": 1644314344, "price_change_number": 22736671}, {"appid": 1401200, "name": "Shadows of Soldiers", "last_modified": 1706807898, "price_change_number": 0}, {"appid": 1401220, "name": "\u51b7\u8840\u75c7\u9ab0\u5b50", "last_modified": 1608113781, "price_change_number": 22774495}, {"appid": 1401320, "name": "\u7834\u955c\u6050\u60e7", "last_modified": 1615173782, "price_change_number": 11351614}, {"appid": 1401340, "name": "Tea Garden Simulator", "last_modified": 1708358901, "price_change_number": 22766324}, {"appid": 1401360, "name": "Friendly Find", "last_modified": 1599252188, "price_change_number": 13116857}, {"appid": 1401370, "name": "Viking City Builder", "last_modified": 1701946960, "price_change_number": 0}, {"appid": 1401400, "name": "Lovecraft's Untold Stories 2", "last_modified": 1706872132, "price_change_number": 22766324}, {"appid": 1401500, "name": "Keep the Lights On", "last_modified": 1688148057, "price_change_number": 22736671}, {"appid": 1401560, "name": "Kilta", "last_modified": 1682086142, "price_change_number": 22766324}, {"appid": 1401570, "name": "Cold Call", "last_modified": 1608810556, "price_change_number": 10335999}, {"appid": 1401590, "name": "Disney Dreamlight Valley", "last_modified": 1709135253, "price_change_number": 22766324}, {"appid": 1401610, "name": "Leons Identit\u00e4t", "last_modified": 1675807267, "price_change_number": 22736671}, {"appid": 1401620, "name": "Chesstle", "last_modified": 1617387652, "price_change_number": 21201610}, {"appid": 1401630, "name": "Stellar Wanderer DX", "last_modified": 1687695698, "price_change_number": 0}, {"appid": 1401670, "name": "Handy Machines VR", "last_modified": 1601478374, "price_change_number": 12598849}, {"appid": 1401680, "name": "Lust from Beyond: Scarlet", "last_modified": 1710333371, "price_change_number": 22736671}, {"appid": 1401730, "name": "Crashlands 2", "last_modified": 1708966407, "price_change_number": 0}, {"appid": 1401750, "name": "Mission Z", "last_modified": 1672684292, "price_change_number": 22716740}, {"appid": 1401840, "name": "Silk Roads: Caravan Kings", "last_modified": 1632225077, "price_change_number": 22766324}, {"appid": 1401870, "name": "Dark Dealings", "last_modified": 1700130178, "price_change_number": 22736671}, {"appid": 1401880, "name": "Midnight Bike", "last_modified": 1600331960, "price_change_number": 22766324}, {"appid": 1401890, "name": "Glorious Tournius", "last_modified": 1619823234, "price_change_number": 15351989}, {"appid": 1401910, "name": "Spellstorm", "last_modified": 1670536760, "price_change_number": 0}, {"appid": 1401940, "name": "\u9732\u9732\u5bfb\u72ac\u8bb0", "last_modified": 1600252237, "price_change_number": 13301447}, {"appid": 1401970, "name": "Galaxy Kart VR", "last_modified": 1704305663, "price_change_number": 21837193}, {"appid": 1401990, "name": "Missing Features: 2D", "last_modified": 1628621412, "price_change_number": 21760363}, {"appid": 1402000, "name": "Trapped Guys", "last_modified": 1604150674, "price_change_number": 22104294}, {"appid": 1402010, "name": "Table Soccer Club", "last_modified": 1608666595, "price_change_number": 13853601}, {"appid": 1402020, "name": "SCP: Labrat", "last_modified": 1675358312, "price_change_number": 22736671}, {"appid": 1402030, "name": "Strings Theory", "last_modified": 1641577562, "price_change_number": 18186143}, {"appid": 1402060, "name": "Dung Beetle Strike", "last_modified": 1602580919, "price_change_number": 15772181}, {"appid": 1402090, "name": "Crisis Wing", "last_modified": 1701774513, "price_change_number": 21760363}, {"appid": 1402110, "name": "Eternights", "last_modified": 1705061719, "price_change_number": 22766324}, {"appid": 1402120, "name": "9 Years of Shadows", "last_modified": 1708869309, "price_change_number": 22766324}, {"appid": 1402130, "name": "Archery Arena", "last_modified": 1611976158, "price_change_number": 12155357}, {"appid": 1402280, "name": "Sensual Slots", "last_modified": 1707424002, "price_change_number": 22328576}, {"appid": 1402290, "name": "Monochrome RPG Episode 1: The Maniacal Morning", "last_modified": 1637276791, "price_change_number": 13179974}, {"appid": 1402320, "name": "Medal of Honor\u2122: Above and Beyond", "last_modified": 1701470786, "price_change_number": 22675672}, {"appid": 1402350, "name": "12 Labours of Hercules XI: Painted Adventure", "last_modified": 1696322041, "price_change_number": 22766324}, {"appid": 1402380, "name": "Hogogeist", "last_modified": 1679714615, "price_change_number": 22766324}, {"appid": 1402400, "name": "Arcanbreak", "last_modified": 1684870737, "price_change_number": 22736671}, {"appid": 1402410, "name": "Funny Business with My Precious Coach (Anipuzzle Series)", "last_modified": 1616583750, "price_change_number": 15820056}, {"appid": 1402420, "name": "Demon Strikes Back", "last_modified": 1661251408, "price_change_number": 22766324}, {"appid": 1402460, "name": "BattleStick 2", "last_modified": 1649662681, "price_change_number": 22736671}, {"appid": 1402580, "name": "No Place for the Dissident", "last_modified": 1605282112, "price_change_number": 16287212}, {"appid": 1402600, "name": "Super Bloo Kid Adventure", "last_modified": 1601394692, "price_change_number": 0}, {"appid": 1402650, "name": "Birding Simulator: Bird Photographer", "last_modified": 1657525876, "price_change_number": 0}, {"appid": 1402700, "name": "Red Falcon", "last_modified": 1609925647, "price_change_number": 10743266}, {"appid": 1402740, "name": "The Prabbits: Happy Dogfights !", "last_modified": 1627730289, "price_change_number": 22411605}, {"appid": 1402780, "name": "Forever Night", "last_modified": 1608619158, "price_change_number": 10317174}, {"appid": 1402790, "name": "Shopping Empire Tycoon", "last_modified": 1684256504, "price_change_number": 22766324}, {"appid": 1402820, "name": "Hostile Mars", "last_modified": 1664826322, "price_change_number": 0}, {"appid": 1402880, "name": "Food War TD", "last_modified": 1602108684, "price_change_number": 0}, {"appid": 1402900, "name": "Twilight Memoria", "last_modified": 1632260099, "price_change_number": 22766324}, {"appid": 1402940, "name": "Graveless\u2122", "last_modified": 1698305877, "price_change_number": 0}, {"appid": 1402960, "name": "Speedily", "last_modified": 1605194518, "price_change_number": 10347109}, {"appid": 1403020, "name": "SCP Strategy", "last_modified": 1688822314, "price_change_number": 22766324}, {"appid": 1403030, "name": "Wanderlost", "last_modified": 1669148860, "price_change_number": 0}, {"appid": 1403040, "name": "Physics Sandbox VR", "last_modified": 1607512675, "price_change_number": 10221020}, {"appid": 1403080, "name": "Radioactive Dwarfs: Evil From The Sewers", "last_modified": 1686845458, "price_change_number": 22766324}, {"appid": 1403110, "name": "Primeval", "last_modified": 1710115348, "price_change_number": 22770607}, {"appid": 1403130, "name": "Pixel Art - Mash-Up", "last_modified": 1600341439, "price_change_number": 12323919}, {"appid": 1403190, "name": "Throne of Fate", "last_modified": 1603391283, "price_change_number": 22766324}, {"appid": 1403230, "name": "Penny RPG: Shadows of the Lost - A Blood City Tale", "last_modified": 1652549027, "price_change_number": 14287222}, {"appid": 1403250, "name": "Underworld Memories", "last_modified": 1638587573, "price_change_number": 0}, {"appid": 1403270, "name": "Genetic Fluff", "last_modified": 1709227185, "price_change_number": 22766324}, {"appid": 1403280, "name": "Struggle Offensive", "last_modified": 1615395698, "price_change_number": 21981215}, {"appid": 1403310, "name": "Garden Simulator", "last_modified": 1708421822, "price_change_number": 22766324}, {"appid": 1403350, "name": "Supfly Delivery Simulator", "last_modified": 1613496495, "price_change_number": 22766324}, {"appid": 1403370, "name": "Zenith: Nexus", "last_modified": 1709061051, "price_change_number": 22736671}, {"appid": 1403400, "name": "Sky Squadron", "last_modified": 1704765834, "price_change_number": 21489524}, {"appid": 1403440, "name": "Broken Roads", "last_modified": 1710430188, "price_change_number": 0}, {"appid": 1403450, "name": "\u754f\u5149", "last_modified": 1604139288, "price_change_number": 0}, {"appid": 1403460, "name": "Flavortown", "last_modified": 1615416233, "price_change_number": 13581874}, {"appid": 1403520, "name": "Forest Farm", "last_modified": 1709954668, "price_change_number": 22766324}, {"appid": 1403550, "name": "Planet Blood", "last_modified": 1606466985, "price_change_number": 22766324}, {"appid": 1403570, "name": "The Message", "last_modified": 1607494837, "price_change_number": 10201942}, {"appid": 1403590, "name": "Kingdom Of Force", "last_modified": 1604398302, "price_change_number": 10743266}, {"appid": 1403650, "name": "Everdream Valley", "last_modified": 1710489449, "price_change_number": 22766324}, {"appid": 1403680, "name": "Bob Mazzolini Racing", "last_modified": 1600163395, "price_change_number": 11428943}, {"appid": 1403710, "name": "Platzkart Simulator", "last_modified": 1612362466, "price_change_number": 21760363}, {"appid": 1403720, "name": "Medulla", "last_modified": 1602879603, "price_change_number": 21312825}, {"appid": 1403740, "name": "Space Architect", "last_modified": 1710384608, "price_change_number": 22766324}, {"appid": 1403750, "name": "\u8857\u673a\u91d1\u87fe\u6355\u9c7c2", "last_modified": 1614844546, "price_change_number": 22736671}, {"appid": 1403830, "name": "Paper Beast - Folded Edition", "last_modified": 1639675070, "price_change_number": 22766324}, {"appid": 1403850, "name": "Mars Colony Builder", "last_modified": 1710239923, "price_change_number": 0}, {"appid": 1403890, "name": "SmFly: Gravity Adventure", "last_modified": 1601655542, "price_change_number": 21760363}, {"appid": 1403940, "name": "Grim", "last_modified": 1701890977, "price_change_number": 0}, {"appid": 1403960, "name": "ATTACK OF THE EVIL POOP VR", "last_modified": 1601571444, "price_change_number": 0}, {"appid": 1403990, "name": "Paths & Danger", "last_modified": 1689009015, "price_change_number": 22766324}, {"appid": 1404010, "name": "A Knight Never Yields", "last_modified": 1614243378, "price_change_number": 18186143}, {"appid": 1404030, "name": "Fighting for Justice Episode 1", "last_modified": 1636674583, "price_change_number": 21489524}, {"appid": 1404050, "name": "10mg: Stroke", "last_modified": 1611588361, "price_change_number": 21760363}, {"appid": 1404070, "name": "Save The Astronaut", "last_modified": 1680759062, "price_change_number": 22716740}, {"appid": 1404080, "name": "Rotund Takeoff", "last_modified": 1650385871, "price_change_number": 21760363}, {"appid": 1404090, "name": "Trivia Tricks", "last_modified": 1708988503, "price_change_number": 22766324}, {"appid": 1404100, "name": "\u56fd\u4ea7\u6e38\u620f\u516c\u53f8\u6a21\u62df", "last_modified": 1639377887, "price_change_number": 0}, {"appid": 1404130, "name": "Gothic Murder: Adventure That Changes Destiny", "last_modified": 1600912878, "price_change_number": 22513184}, {"appid": 1404150, "name": "Escape the City", "last_modified": 1603466363, "price_change_number": 22513184}, {"appid": 1404160, "name": "Mega Capital", "last_modified": 1601456381, "price_change_number": 0}, {"appid": 1404180, "name": "6th Dimension", "last_modified": 1601070143, "price_change_number": 22736671}, {"appid": 1404190, "name": "Chess Brain", "last_modified": 1621027485, "price_change_number": 22789685}, {"appid": 1404210, "name": "Red Dead Online", "last_modified": 1656615218, "price_change_number": 22766324}, {"appid": 1404240, "name": "\u041f\u0443\u0442\u0438\u043d \u043f\u0440\u043e\u0442\u0438\u0432 \u0418\u043d\u043e\u043f\u043b\u0430\u043d\u0435\u0442\u044f\u043d: \u0424\u0438\u043d\u0430\u043b (CyberPutin 2077: Endgame)", "last_modified": 1599045113, "price_change_number": 0}, {"appid": 1404300, "name": "Drops of Death", "last_modified": 1707504846, "price_change_number": 0}, {"appid": 1404330, "name": "VR Quiet Life", "last_modified": 1674221113, "price_change_number": 22766324}, {"appid": 1404360, "name": "A Shopping Trip to Eklan Tor", "last_modified": 1614371049, "price_change_number": 22736671}, {"appid": 1404450, "name": "Godo", "last_modified": 1613785078, "price_change_number": 10839776}, {"appid": 1404490, "name": "Cursed Weekend", "last_modified": 1613987192, "price_change_number": 0}, {"appid": 1404520, "name": "Death Blonde", "last_modified": 1699863098, "price_change_number": 0}, {"appid": 1404530, "name": "RoboSkate", "last_modified": 1613394298, "price_change_number": 22766324}, {"appid": 1404550, "name": "Legend of Xion: Royal Story \u8d5b\u6069\u4f20\u8bf4\uff1a\u7687\u5bb6\u7269\u8bed", "last_modified": 1606649128, "price_change_number": 22766324}, {"appid": 1404560, "name": "Yerba Mate Tycoon", "last_modified": 1631070896, "price_change_number": 22766324}, {"appid": 1404630, "name": "All Hit All Her", "last_modified": 1697089474, "price_change_number": 22766324}, {"appid": 1404660, "name": "Psych", "last_modified": 1686335320, "price_change_number": 22766324}]